Workbook
Name Slicer_Month: #N/A
Name Slicer_Year: #N/A
Name start_day: #REF!

Sheet General Calendar
C3: This calendar show only Deadlines for every Finance Team commitment. Each team should organize their workstreams to present reviewed & final deliverables and fulfill each task on the deadline date.
C4: For more detail use the following schedule: | E4: Detailed Tasks
K5: ▪ | L5: Click on Month list (G7) to view one team member only
C6: Finance Team Commitments | G6: Month | H6: Year | I6: Main Owner / Entire Team | K6: ▪ | L6: Click on Year list (H7) to view one team member only
G7: July | H7: 2025 | I7: Finance Manager | K7: ▪ | L7: Click on Main Owner list (I7) to view one team member only
K8: ▪ | L8: Click on Detailed Task (E4) to view team members involved
C9: Sunday | D9: Monday | E9: Tuesday | F9: Wednesday | G9: Thursday | H9: Friday | I9: Saturday
C10: =_xlfn.IFNA(_xlfn.XLOOKUP(C11,'Date master'!$E:$E,'Date master'!$I:$I),"") | D10: =_xlfn.IFNA(_xlfn.XLOOKUP(D11,'Date master'!$E:$E,'Date master'!$I:$I),"") | E10: =_xlfn.IFNA(_xlfn.XLOOKUP(E11,'Date master'!$E:$E,'Date master'!$I:$I),"") -> 1 | F10: =_xlfn.IFNA(_xlfn.XLOOKUP(F11,'Date master'!$E:$E,'Date master'!$I:$I),"") -> 2 | G10: =_xlfn.IFNA(_xlfn.XLOOKUP(G11,'Date master'!$E:$E,'Date master'!$I:$I),"") -> 3 | H10: =_xlfn.IFNA(_xlfn.XLOOKUP(H11,'Date master'!$E:$E,'Date master'!$I:$I),"") | I10: =_xlfn.IFNA(_xlfn.XLOOKUP(I11,'Date master'!$E:$E,'Date master'!$I:$I),"")
C11: =DATEVALUE(1&$G$7&$H$7)-WEEKDAY(DATEVALUE(1&$G$7&$H$7),2) -> 45837 | D11: =C11+1 -> 45838 | E11: =D11+1 -> 45839 | F11: =E11+1 -> 45840 | G11: =F11+1 -> 45841 | H11: =G11+1 -> 45842 | I11: =H11+1 -> 45843
C12: {=IFERROR( _xlfn.TEXTJOIN(CHAR(10), TRUE, _xlfn._xlws.FILTER( "- " & 'Commitments & Ownership Matrix'!$B$5:$B$30, ( ( ($I$7="Entire Team") * ('Commitments & Ownership Matrix'!$D$5:$D$30=C10) + (('Commitments & Ownership Matrix'!$F$5:$F$30=$I$7) * ('Commitments & Ownership Matrix'!$D$5:$D$30=C10)) ) * ('Commitments & Ownership Matrix'!$B$5:$B$30 <> "") ) ) ), "" )} | D12: {=IFERROR( _xlfn.TEXTJOIN(CHAR(10), TRUE, _xlfn._xlws.FILTER( "- " & 'Commitments & Ownership Matrix'!$B$5:$B$30, ( ( ($I$7="Entire Team") * ('Commitments & Ownership Matrix'!$D$5:$D$30=D10) + (('Commitments & Ownership Matrix'!$F$5:$F$30=$I$7) * ('Commitments & Ownership Matrix'!$D$5:$D$30=D10)) ) * ('Commitments & Ownership Matrix'!$B$5:$B$30 <> "") ) ) ), "" )} | E12: {=IFERROR( _xlfn.TEXTJOIN(CHAR(10), TRUE, _xlfn._xlws.FILTER( "- " & 'Commitments & Ownership Matrix'!$B$5:$B$30, ( ( ($I$7="Entire Team") * ('Commitments & Ownership Matrix'!$D$5:$D$30=E10) + (('Commitments & Ownership Matrix'!$F$5:$F$30=$I$7) * ('Commitments & Ownership Matrix'!$D$5:$D$30=E10)) ) * ('Commitments & Ownership Matrix'!$B$5:$B$30 <> "") ) ) ), "" )} | F12: {=IFERROR( _xlfn.TEXTJOIN(CHAR(10), TRUE, _xlfn._xlws.FILTER( "- " & 'Commitments & Ownership Matrix'!$B$5:$B$30, ( ( ($I$7="Entire Team") * ('Commitments & Ownership Matrix'!$D$5:$D$30=F10) + (('Commitments & Ownership Matrix'!$F$5:$F$30=$I$7) * ('Commitments & Ownership Matrix'!$D$5:$D$30=F10)) ) * ('Commitments & Ownership Matrix'!$B$5:$B$30 <> "") ) ) ), "" )} | G12: {=IFERROR( _xlfn.TEXTJOIN(CHAR(10), TRUE, _xlfn._xlws.FILTER( "- " & 'Commitments & Ownership Matrix'!$B$5:$B$30, ( ( ($I$7="Entire Team") * ('Commitments & Ownership Matrix'!$D$5:$D$30=G10) + (('Commitments & Ownership Matrix'!$F$5:$F$30=$I$7) * ('Commitments & Ownership Matrix'!$D$5:$D$30=G10)) ) * ('Commitments & Ownership Matrix'!$B$5:$B$30 <> "") ) ) ), "" )} | H12: {=IFERROR( _xlfn.TEXTJOIN(CHAR(10), TRUE, _xlfn._xlws.FILTER( "- " & 'Commitments & Ownership Matrix'!$B$5:$B$30, ( ( ($I$7="Entire Team") * ('Commitments & Ownership Matrix'!$D$5:$D$30=H10) + (('Commitments & Ownership Matrix'!$F$5:$F$30=$I$7) * ('Commitments & Ownership Matrix'!$D$5:$D$30=H10)) ) * ('Commitments & Ownership Matrix'!$B$5:$B$30 <> "") ) ) ), "" )} | I12: {=IFERROR( _xlfn.TEXTJOIN(CHAR(10), TRUE, _xlfn._xlws.FILTER( "- " & 'Commitments & Ownership Matrix'!$B$5:$B$30, ( ( ($I$7="Entire Team") * ('Commitments & Ownership Matrix'!$D$5:$D$30=I10) + (('Commitments & Ownership Matrix'!$F$5:$F$30=$I$7) * ('Commitments & Ownership Matrix'!$D$5:$D$30=I10)) ) * ('Commitments & Ownership Matrix'!$B$5:$B$30 <> "") ) ) ), "" )}
C13: {=IFERROR( _xlfn.TEXTJOIN(CHAR(10), TRUE, _xlfn._xlws.FILTER( "- " & 'Commitments & Ownership Matrix'!$B$5:$B$40, ( (($I$7="Entire Team") * ('Commitments & Ownership Matrix'!$E$5:$E$40=C11)) + (('Commitments & Ownership Matrix'!$F$5:$F$40=$I$7) * ('Commitments & Ownership Matrix'!$E$5:$E$40=C11)) ) * ('Commitments & Ownership Matrix'!$H$5:$H$40="Exceptional") * ('Commitments & Ownership Matrix'!$B$5:$B$40<>"") ) ), "" )} | D13: {=IFERROR( _xlfn.TEXTJOIN(CHAR(10), TRUE, _xlfn._xlws.FILTER( "- " & 'Commitments & Ownership Matrix'!$B$5:$B$40, ( (($I$7="Entire Team") * ('Commitments & Ownership Matrix'!$E$5:$E$40=D11)) + (('Commitments & Ownership Matrix'!$F$5:$F$40=$I$7) * ('Commitments & Ownership Matrix'!$E$5:$E$40=D11)) ) * ('Commitments & Ownership Matrix'!$H$5:$H$40="Exceptional") * ('Commitments & Ownership Matrix'!$B$5:$B$40<>"") ) ), "" )} | E13: {=IFERROR( _xlfn.TEXTJOIN(CHAR(10), TRUE, _xlfn._xlws.FILTER( "- " & 'Commitments & Ownership Matrix'!$B$5:$B$40, ( (($I$7="Entire Team") * ('Commitments & Ownership Matrix'!$E$5:$E$40=E11)) + (('Commitments & Ownership Matrix'!$F$5:$F$40=$I$7) * ('Commitments & Ownership Matrix'!$E$5:$E$40=E11)) ) * ('Commitments & Ownership Matrix'!$H$5:$H$40="Exceptional") * ('Commitments & Ownership Matrix'!$B$5:$B$40<>"") ) ), "" )} | F13: {=IFERROR( _xlfn.TEXTJOIN(CHAR(10), TRUE, _xlfn._xlws.FILTER( "- " & 'Commitments & Ownership Matrix'!$B$5:$B$40, ( (($I$7="Entire Team") * ('Commitments & Ownership Matrix'!$E$5:$E$40=F11)) + (('Commitments & Ownership Matrix'!$F$5:$F$40=$I$7) * ('Commitments & Ownership Matrix'!$E$5:$E$40=F11)) ) * ('Commitments & Ownership Matrix'!$H$5:$H$40="Exceptional") * ('Commitments & Ownership Matrix'!$B$5:$B$40<>"") ) ), "" )} | G13: {=IFERROR( _xlfn.TEXTJOIN(CHAR(10), TRUE, _xlfn._xlws.FILTER( "- " & 'Commitments & Ownership Matrix'!$B$5:$B$40, ( (($I$7="Entire Team") * ('Commitments & Ownership Matrix'!$E$5:$E$40=G11)) + (('Commitments & Ownership Matrix'!$F$5:$F$40=$I$7) * ('Commitments & Ownership Matrix'!$E$5:$E$40=G11)) ) * ('Commitments & Ownership Matrix'!$H$5:$H$40="Exceptional") * ('Commitments & Ownership Matrix'!$B$5:$B$40<>"") ) ), "" )} | H13: {=IFERROR( _xlfn.TEXTJOIN(CHAR(10), TRUE, _xlfn._xlws.FILTER( "- " & 'Commitments & Ownership Matrix'!$B$5:$B$40, ( (($I$7="Entire Team") * ('Commitments & Ownership Matrix'!$E$5:$E$40=H11)) + (('Commitments & Ownership Matrix'!$F$5:$F$40=$I$7) * ('Commitments & Ownership Matrix'!$E$5:$E$40=H11)) ) * ('Commitments & Ownership Matrix'!$H$5:$H$40="Exceptional") * ('Commitments & Ownership Matrix'!$B$5:$B$40<>"") ) ), "" )} | I13: {=IFERROR( _xlfn.TEXTJOIN(CHAR(10), TRUE, _xlfn._xlws.FILTER( "- " & 'Commitments & Ownership Matrix'!$B$5:$B$40, ( (($I$7="Entire Team") * ('Commitments & Ownership Matrix'!$E$5:$E$40=I11)) + (('Commitments & Ownership Matrix'!$F$5:$F$40=$I$7) * ('Commitments & Ownership Matrix'!$E$5:$E$40=I11)) ) * ('Commitments & Ownership Matrix'!$H$5:$H$40="Exceptional") * ('Commitments & Ownership Matrix'!$B$5:$B$40<>"") ) ), "" )}
D14: =_xlfn.XLOOKUP(D11, 'Date master'!$E:$E,'Date master'!$F:$F, "") & " " & _xlfn.XLOOKUP(D11, 'Date master'!$E:$E, 'Date master'!$G:$G, "") | E14: =_xlfn.XLOOKUP(E11, 'Date master'!$E:$E,'Date master'!$F:$F, "") & " " & _xlfn.XLOOKUP(E11, 'Date master'!$E:$E, 'Date master'!$G:$G, "") | F14: =_xlfn.XLOOKUP(F11, 'Date master'!$E:$E,'Date master'!$F:$F, "") & " " & _xlfn.XLOOKUP(F11, 'Date master'!$E:$E, 'Date master'!$G:$G, "") | G14: =_xlfn.XLOOKUP(G11, 'Date master'!$E:$E,'Date master'!$F:$F, "") & " " & _xlfn.XLOOKUP(G11, 'Date master'!$E:$E, 'Date master'!$G:$G, "") | H14: =_xlfn.XLOOKUP(H11, 'Date master'!$E:$E,'Date master'!$F:$F, "") & " " & _xlfn.XLOOKUP(H11, 'Date master'!$E:$E, 'Date master'!$G:$G, "") -> US Independence Day
C15: =_xlfn.IFNA(_xlfn.XLOOKUP(C16,'Date master'!$E:$E,'Date master'!$I:$I),"") | D15: =_xlfn.IFNA(_xlfn.XLOOKUP(D16,'Date master'!$E:$E,'Date master'!$I:$I),"") -> 4 | E15: =_xlfn.IFNA(_xlfn.XLOOKUP(E16,'Date master'!$E:$E,'Date master'!$I:$I),"") -> 5 | F15: =_xlfn.IFNA(_xlfn.XLOOKUP(F16,'Date master'!$E:$E,'Date master'!$I:$I),"") -> 6 | G15: =_xlfn.IFNA(_xlfn.XLOOKUP(G16,'Date master'!$E:$E,'Date master'!$I:$I),"") -> 7 | H15: =_xlfn.IFNA(_xlfn.XLOOKUP(H16,'Date master'!$E:$E,'Date master'!$I:$I),"") -> 8 | I15: =_xlfn.IFNA(_xlfn.XLOOKUP(I16,'Date master'!$E:$E,'Date master'!$I:$I),"")
C16: =C11+7 -> 45844 | D16: =D11+7 -> 45845 | E16: =E11+7 -> 45846 | F16: =F11+7 -> 45847 | G16: =G11+7 -> 45848 | H16: =H11+7 -> 45849 | I16: =I11+7 -> 45850
C17: {=IFERROR( _xlfn.TEXTJOIN(CHAR(10), TRUE, _xlfn._xlws.FILTER( "- " & 'Commitments & Ownership Matrix'!$B$5:$B$30, ( ( ($I$7="Entire Team") * ('Commitments & Ownership Matrix'!$D$5:$D$30=C15) + (('Commitments & Ownership Matrix'!$F$5:$F$30=$I$7) * ('Commitments & Ownership Matrix'!$D$5:$D$30=C15)) ) * ('Commitments & Ownership Matrix'!$B$5:$B$30 <> "") ) ) ), "" )} | D17: {=IFERROR( _xlfn.TEXTJOIN(CHAR(10), TRUE, _xlfn._xlws.FILTER( "- " & 'Commitments & Ownership Matrix'!$B$5:$B$30, ( ( ($I$7="Entire Team") * ('Commitments & Ownership Matrix'!$D$5:$D$30=D15) + (('Commitments & Ownership Matrix'!$F$5:$F$30=$I$7) * ('Commitments & Ownership Matrix'!$D$5:$D$30=D15)) ) * ('Commitments & Ownership Matrix'!$B$5:$B$30 <> "") ) ) ), "" )} | E17: {=IFERROR( _xlfn.TEXTJOIN(CHAR(10), TRUE, _xlfn._xlws.FILTER( "- " & 'Commitments & Ownership Matrix'!$B$5:$B$30, ( ( ($I$7="Entire Team") * ('Commitments & Ownership Matrix'!$D$5:$D$30=E15) + (('Commitments & Ownership Matrix'!$F$5:$F$30=$I$7) * ('Commitments & Ownership Matrix'!$D$5:$D$30=E15)) ) * ('Commitments & Ownership Matrix'!$B$5:$B$30 <> "") ) ) ), "" )} -> - Accrued Expenses | F17: {=IFERROR( _xlfn.TEXTJOIN(CHAR(10), TRUE, _xlfn._xlws.FILTER( "- " & 'Commitments & Ownership Matrix'!$B$5:$B$30, ( ( ($I$7="Entire Team") * ('Commitments & Ownership Matrix'!$D$5:$D$30=F15) + (('Commitments & Ownership Matrix'!$F$5:$F$30=$I$7) * ('Commitments & Ownership Matrix'!$D$5:$D$30=F15)) ) * ('Commitments & Ownership Matrix'!$B$5:$B$30 <> "") ) ) ), "" )} -> - Banking | G17: {=IFERROR( _xlfn.TEXTJOIN(CHAR(10), TRUE, _xlfn._xlws.FILTER( "- " & 'Commitments & Ownership Matrix'!$B$5:$B$30, ( ( ($I$7="Entire Team") * ('Commitments & Ownership Matrix'!$D$5:$D$30=G15) + (('Commitments & Ownership Matrix'!$F$5:$F$30=$I$7) * ('Commitments & Ownership Matrix'!$D$5:$D$30=G15)) ) * ('Commitments & Ownership Matrix'!$B$5:$B$30 <> "") ) ) ), "" )} | H17: {=IFERROR( _xlfn.TEXTJOIN(CHAR(10), TRUE, _xlfn._xlws.FILTER( "- " & 'Commitments & Ownership Matrix'!$B$5:$B$30, ( ( ($I$7="Entire Team") * ('Commitments & Ownership Matrix'!$D$5:$D$30=H15) + (('Commitments & Ownership Matrix'!$F$5:$F$30=$I$7) * ('Commitments & Ownership Matrix'!$D$5:$D$30=H15)) ) * ('Commitments & Ownership Matrix'!$B$5:$B$30 <> "") ) ) ), "" )} | I17: {=IFERROR( _xlfn.TEXTJOIN(CHAR(10), TRUE, _xlfn._xlws.FILTER( "- " & 'Commitments & Ownership Matrix'!$B$5:$B$30, ( ( ($I$7="Entire Team") * ('Commitments & Ownership Matrix'!$D$5:$D$30=I15) + (('Commitments & Ownership Matrix'!$F$5:$F$30=$I$7) * ('Commitments & Ownership Matrix'!$D$5:$D$30=I15)) ) * ('Commitments & Ownership Matrix'!$B$5:$B$30 <> "") ) ) ), "" )}
C18: {=IFERROR( _xlfn.TEXTJOIN(CHAR(10), TRUE, _xlfn._xlws.FILTER( "- " & 'Commitments & Ownership Matrix'!$B$5:$B$40, ( (($I$7="Entire Team") * ('Commitments & Ownership Matrix'!$E$5:$E$40=C16)) + (('Commitments & Ownership Matrix'!$F$5:$F$40=$I$7) * ('Commitments & Ownership Matrix'!$E$5:$E$40=C16)) ) * ('Commitments & Ownership Matrix'!$H$5:$H$40="Exceptional") * ('Commitments & Ownership Matrix'!$B$5:$B$40<>"") ) ), "" )} | D18: {=IFERROR( _xlfn.TEXTJOIN(CHAR(10), TRUE, _xlfn._xlws.FILTER( "- " & 'Commitments & Ownership Matrix'!$B$5:$B$40, ( (($I$7="Entire Team") * ('Commitments & Ownership Matrix'!$E$5:$E$40=D16)) + (('Commitments & Ownership Matrix'!$F$5:$F$40=$I$7) * ('Commitments & Ownership Matrix'!$E$5:$E$40=D16)) ) * ('Commitments & Ownership Matrix'!$H$5:$H$40="Exceptional") * ('Commitments & Ownership Matrix'!$B$5:$B$40<>"") ) ), "" )} | E18: {=IFERROR( _xlfn.TEXTJOIN(CHAR(10), TRUE, _xlfn._xlws.FILTER( "- " & 'Commitments & Ownership Matrix'!$B$5:$B$40, ( (($I$7="Entire Team") * ('Commitments & Ownership Matrix'!$E$5:$E$40=E16)) + (('Commitments & Ownership Matrix'!$F$5:$F$40=$I$7) * ('Commitments & Ownership Matrix'!$E$5:$E$40=E16)) ) * ('Commitments & Ownership Matrix'!$H$5:$H$40="Exceptional") * ('Commitments & Ownership Matrix'!$B$5:$B$40<>"") ) ), "" )} | F18: {=IFERROR( _xlfn.TEXTJOIN(CHAR(10), TRUE, _xlfn._xlws.FILTER( "- " & 'Commitments & Ownership Matrix'!$B$5:$B$40, ( (($I$7="Entire Team") * ('Commitments & Ownership Matrix'!$E$5:$E$40=F16)) + (('Commitments & Ownership Matrix'!$F$5:$F$40=$I$7) * ('Commitments & Ownership Matrix'!$E$5:$E$40=F16)) ) * ('Commitments & Ownership Matrix'!$H$5:$H$40="Exceptional") * ('Commitments & Ownership Matrix'!$B$5:$B$40<>"") ) ), "" )} | G18: {=IFERROR( _xlfn.TEXTJOIN(CHAR(10), TRUE, _xlfn._xlws.FILTER( "- " & 'Commitments & Ownership Matrix'!$B$5:$B$40, ( (($I$7="Entire Team") * ('Commitments & Ownership Matrix'!$E$5:$E$40=G16)) + (('Commitments & Ownership Matrix'!$F$5:$F$40=$I$7) * ('Commitments & Ownership Matrix'!$E$5:$E$40=G16)) ) * ('Commitments & Ownership Matrix'!$H$5:$H$40="Exceptional") * ('Commitments & Ownership Matrix'!$B$5:$B$40<>"") ) ), "" )} | H18: {=IFERROR( _xlfn.TEXTJOIN(CHAR(10), TRUE, _xlfn._xlws.FILTER( "- " & 'Commitments & Ownership Matrix'!$B$5:$B$40, ( (($I$7="Entire Team") * ('Commitments & Ownership Matrix'!$E$5:$E$40=H16)) + (('Commitments & Ownership Matrix'!$F$5:$F$40=$I$7) * ('Commitments & Ownership Matrix'!$E$5:$E$40=H16)) ) * ('Commitments & Ownership Matrix'!$H$5:$H$40="Exceptional") * ('Commitments & Ownership Matrix'!$B$5:$B$40<>"") ) ), "" )} | I18: {=IFERROR( _xlfn.TEXTJOIN(CHAR(10), TRUE, _xlfn._xlws.FILTER( "- " & 'Commitments & Ownership Matrix'!$B$5:$B$40, ( (($I$7="Entire Team") * ('Commitments & Ownership Matrix'!$E$5:$E$40=I16)) + (('Commitments & Ownership Matrix'!$F$5:$F$40=$I$7) * ('Commitments & Ownership Matrix'!$E$5:$E$40=I16)) ) * ('Commitments & Ownership Matrix'!$H$5:$H$40="Exceptional") * ('Commitments & Ownership Matrix'!$B$5:$B$40<>"") ) ), "" )}
D19: =_xlfn.XLOOKUP(D16, 'Date master'!$E:$E,'Date master'!$F:$F, "") & " " & _xlfn.XLOOKUP(D16, 'Date master'!$E:$E, 'Date master'!$G:$G, "") | E19: =_xlfn.XLOOKUP(E16, 'Date master'!$E:$E,'Date master'!$F:$F, "") & " " & _xlfn.XLOOKUP(E16, 'Date master'!$E:$E, 'Date master'!$G:$G, "") | F19: =_xlfn.XLOOKUP(F16, 'Date master'!$E:$E,'Date master'!$F:$F, "") & " " & _xlfn.XLOOKUP(F16, 'Date master'!$E:$E, 'Date master'!$G:$G, "") | G19: =_xlfn.XLOOKUP(G16, 'Date master'!$E:$E,'Date master'!$F:$F, "") & " " & _xlfn.XLOOKUP(G16, 'Date master'!$E:$E, 'Date master'!$G:$G, "") | H19: =_xlfn.XLOOKUP(H16, 'Date master'!$E:$E,'Date master'!$F:$F, "") & " " & _xlfn.XLOOKUP(H16, 'Date master'!$E:$E, 'Date master'!$G:$G, "")
C20: =_xlfn.IFNA(_xlfn.XLOOKUP(C21,'Date master'!$E:$E,'Date master'!$I:$I),"") | D20: =_xlfn.IFNA(_xlfn.XLOOKUP(D21,'Date master'!$E:$E,'Date master'!$I:$I),"") -> 9 | E20: =_xlfn.IFNA(_xlfn.XLOOKUP(E21,'Date master'!$E:$E,'Date master'!$I:$I),"") -> 10 | F20: =_xlfn.IFNA(_xlfn.XLOOKUP(F21,'Date master'!$E:$E,'Date master'!$I:$I),"") -> 11 | G20: =_xlfn.IFNA(_xlfn.XLOOKUP(G21,'Date master'!$E:$E,'Date master'!$I:$I),"") -> 12 | H20: =_xlfn.IFNA(_xlfn.XLOOKUP(H21,'Date master'!$E:$E,'Date master'!$I:$I),"") -> 13 | I20: =_xlfn.IFNA(_xlfn.XLOOKUP(I21,'Date master'!$E:$E,'Date master'!$I:$I),"")
C21: =C16+7 -> 45851 | D21: =D16+7 -> 45852 | E21: =E16+7 -> 45853 | F21: =F16+7 -> 45854 | G21: =G16+7 -> 45855 | H21: =H16+7 -> 45856 | I21: =I16+7 -> 45857
C22: {=IFERROR( _xlfn.TEXTJOIN(CHAR(10), TRUE, _xlfn._xlws.FILTER( "- " & 'Commitments & Ownership Matrix'!$B$5:$B$30, ( ( ($I$7="Entire Team") * ('Commitments & Ownership Matrix'!$D$5:$D$30=C20) + (('Commitments & Ownership Matrix'!$F$5:$F$30=$I$7) * ('Commitments & Ownership Matrix'!$D$5:$D$30=C20)) ) * ('Commitments & Ownership Matrix'!$B$5:$B$30 <> "") ) ) ), "" )} | D22: {=IFERROR( _xlfn.TEXTJOIN(CHAR(10), TRUE, _xlfn._xlws.FILTER( "- " & 'Commitments & Ownership Matrix'!$B$5:$B$30, ( ( ($I$7="Entire Team") * ('Commitments & Ownership Matrix'!$D$5:$D$30=D20) + (('Commitments & Ownership Matrix'!$F$5:$F$30=$I$7) * ('Commitments & Ownership Matrix'!$D$5:$D$30=D20)) ) * ('Commitments & Ownership Matrix'!$B$5:$B$30 <> "") ) ) ), "" )} | E22: {=IFERROR( _xlfn.TEXTJOIN(CHAR(10), TRUE, _xlfn._xlws.FILTER( "- " & 'Commitments & Ownership Matrix'!$B$5:$B$30, ( ( ($I$7="Entire Team") * ('Commitments & Ownership Matrix'!$D$5:$D$30=E20) + (('Commitments & Ownership Matrix'!$F$5:$F$30=$I$7) * ('Commitments & Ownership Matrix'!$D$5:$D$30=E20)) ) * ('Commitments & Ownership Matrix'!$B$5:$B$30 <> "") ) ) ), "" )} | F22: {=IFERROR( _xlfn.TEXTJOIN(CHAR(10), TRUE, _xlfn._xlws.FILTER( "- " & 'Commitments & Ownership Matrix'!$B$5:$B$30, ( ( ($I$7="Entire Team") * ('Commitments & Ownership Matrix'!$D$5:$D$30=F20) + (('Commitments & Ownership Matrix'!$F$5:$F$30=$I$7) * ('Commitments & Ownership Matrix'!$D$5:$D$30=F20)) ) * ('Commitments & Ownership Matrix'!$B$5:$B$30 <> "") ) ) ), "" )} | G22: {=IFERROR( _xlfn.TEXTJOIN(CHAR(10), TRUE, _xlfn._xlws.FILTER( "- " & 'Commitments & Ownership Matrix'!$B$5:$B$30, ( ( ($I$7="Entire Team") * ('Commitments & Ownership Matrix'!$D$5:$D$30=G20) + (('Commitments & Ownership Matrix'!$F$5:$F$30=$I$7) * ('Commitments & Ownership Matrix'!$D$5:$D$30=G20)) ) * ('Commitments & Ownership Matrix'!$B$5:$B$30 <> "") ) ) ), "" )} | H22: {=IFERROR( _xlfn.TEXTJOIN(CHAR(10), TRUE, _xlfn._xlws.FILTER( "- " & 'Commitments & Ownership Matrix'!$B$5:$B$30, ( ( ($I$7="Entire Team") * ('Commitments & Ownership Matrix'!$D$5:$D$30=H20) + (('Commitments & Ownership Matrix'!$F$5:$F$30=$I$7) * ('Commitments & Ownership Matrix'!$D$5:$D$30=H20)) ) * ('Commitments & Ownership Matrix'!$B$5:$B$30 <> "") ) ) ), "" )} | I22: {=IFERROR( _xlfn.TEXTJOIN(CHAR(10), TRUE, _xlfn._xlws.FILTER( "- " & 'Commitments & Ownership Matrix'!$B$5:$B$30, ( ( ($I$7="Entire Team") * ('Commitments & Ownership Matrix'!$D$5:$D$30=I20) + (('Commitments & Ownership Matrix'!$F$5:$F$30=$I$7) * ('Commitments & Ownership Matrix'!$D$5:$D$30=I20)) ) * ('Commitments & Ownership Matrix'!$B$5:$B$30 <> "") ) ) ), "" )}
C23: {=IFERROR( _xlfn.TEXTJOIN(CHAR(10), TRUE, _xlfn._xlws.FILTER( "- " & 'Commitments & Ownership Matrix'!$B$5:$B$40, ( (($I$7="Entire Team") * ('Commitments & Ownership Matrix'!$E$5:$E$40=C21)) + (('Commitments & Ownership Matrix'!$F$5:$F$40=$I$7) * ('Commitments & Ownership Matrix'!$E$5:$E$40=C21)) ) * ('Commitments & Ownership Matrix'!$H$5:$H$40="Exceptional") * ('Commitments & Ownership Matrix'!$B$5:$B$40<>"") ) ), "" )} | D23: {=IFERROR( _xlfn.TEXTJOIN(CHAR(10), TRUE, _xlfn._xlws.FILTER( "- " & 'Commitments & Ownership Matrix'!$B$5:$B$40, ( (($I$7="Entire Team") * ('Commitments & Ownership Matrix'!$E$5:$E$40=D21)) + (('Commitments & Ownership Matrix'!$F$5:$F$40=$I$7) * ('Commitments & Ownership Matrix'!$E$5:$E$40=D21)) ) * ('Commitments & Ownership Matrix'!$H$5:$H$40="Exceptional") * ('Commitments & Ownership Matrix'!$B$5:$B$40<>"") ) ), "" )} | E23: {=IFERROR( _xlfn.TEXTJOIN(CHAR(10), TRUE, _xlfn._xlws.FILTER( "- " & 'Commitments & Ownership Matrix'!$B$5:$B$40, ( (($I$7="Entire Team") * ('Commitments & Ownership Matrix'!$E$5:$E$40=E21)) + (('Commitments & Ownership Matrix'!$F$5:$F$40=$I$7) * ('Commitments & Ownership Matrix'!$E$5:$E$40=E21)) ) * ('Commitments & Ownership Matrix'!$H$5:$H$40="Exceptional") * ('Commitments & Ownership Matrix'!$B$5:$B$40<>"") ) ), "" )} | F23: {=IFERROR( _xlfn.TEXTJOIN(CHAR(10), TRUE, _xlfn._xlws.FILTER( "- " & 'Commitments & Ownership Matrix'!$B$5:$B$40, ( (($I$7="Entire Team") * ('Commitments & Ownership Matrix'!$E$5:$E$40=F21)) + (('Commitments & Ownership Matrix'!$F$5:$F$40=$I$7) * ('Commitments & Ownership Matrix'!$E$5:$E$40=F21)) ) * ('Commitments & Ownership Matrix'!$H$5:$H$40="Exceptional") * ('Commitments & Ownership Matrix'!$B$5:$B$40<>"") ) ), "" )} | G23: {=IFERROR( _xlfn.TEXTJOIN(CHAR(10), TRUE, _xlfn._xlws.FILTER( "- " & 'Commitments & Ownership Matrix'!$B$5:$B$40, ( (($I$7="Entire Team") * ('Commitments & Ownership Matrix'!$E$5:$E$40=G21)) + (('Commitments & Ownership Matrix'!$F$5:$F$40=$I$7) * ('Commitments & Ownership Matrix'!$E$5:$E$40=G21)) ) * ('Commitments & Ownership Matrix'!$H$5:$H$40="Exceptional") * ('Commitments & Ownership Matrix'!$B$5:$B$40<>"") ) ), "" )} | H23: {=IFERROR( _xlfn.TEXTJOIN(CHAR(10), TRUE, _xlfn._xlws.FILTER( "- " & 'Commitments & Ownership Matrix'!$B$5:$B$40, ( (($I$7="Entire Team") * ('Commitments & Ownership Matrix'!$E$5:$E$40=H21)) + (('Commitments & Ownership Matrix'!$F$5:$F$40=$I$7) * ('Commitments & Ownership Matrix'!$E$5:$E$40=H21)) ) * ('Commitments & Ownership Matrix'!$H$5:$H$40="Exceptional") * ('Commitments & Ownership Matrix'!$B$5:$B$40<>"") ) ), "" )} | I23: {=IFERROR( _xlfn.TEXTJOIN(CHAR(10), TRUE, _xlfn._xlws.FILTER( "- " & 'Commitments & Ownership Matrix'!$B$5:$B$40, ( (($I$7="Entire Team") * ('Commitments & Ownership Matrix'!$E$5:$E$40=I21)) + (('Commitments & Ownership Matrix'!$F$5:$F$40=$I$7) * ('Commitments & Ownership Matrix'!$E$5:$E$40=I21)) ) * ('Commitments & Ownership Matrix'!$H$5:$H$40="Exceptional") * ('Commitments & Ownership Matrix'!$B$5:$B$40<>"") ) ), "" )}
D24: =_xlfn.XLOOKUP(D21, 'Date master'!$E:$E,'Date master'!$F:$F, "") & " " & _xlfn.XLOOKUP(D21, 'Date master'!$E:$E, 'Date master'!$G:$G, "") | E24: =_xlfn.XLOOKUP(E21, 'Date master'!$E:$E,'Date master'!$F:$F, "") & " " & _xlfn.XLOOKUP(E21, 'Date master'!$E:$E, 'Date master'!$G:$G, "") | F24: =_xlfn.XLOOKUP(F21, 'Date master'!$E:$E,'Date master'!$F:$F, "") & " " & _xlfn.XLOOKUP(F21, 'Date master'!$E:$E, 'Date master'!$G:$G, "") | G24: =_xlfn.XLOOKUP(G21, 'Date master'!$E:$E,'Date master'!$F:$F, "") & " " & _xlfn.XLOOKUP(G21, 'Date master'!$E:$E, 'Date master'!$G:$G, "") | H24: =_xlfn.XLOOKUP(H21, 'Date master'!$E:$E,'Date master'!$F:$F, "") & " " & _xlfn.XLOOKUP(H21, 'Date master'!$E:$E, 'Date master'!$G:$G, "")
C25: =_xlfn.IFNA(_xlfn.XLOOKUP(C26,'Date master'!$E:$E,'Date master'!$I:$I),"") | D25: =_xlfn.IFNA(_xlfn.XLOOKUP(D26,'Date master'!$E:$E,'Date master'!$I:$I),"") -> 14 | E25: =_xlfn.IFNA(_xlfn.XLOOKUP(E26,'Date master'!$E:$E,'Date master'!$I:$I),"") -> 15 | F25: =_xlfn.IFNA(_xlfn.XLOOKUP(F26,'Date master'!$E:$E,'Date master'!$I:$I),"") -> 16 | G25: =_xlfn.IFNA(_xlfn.XLOOKUP(G26,'Date master'!$E:$E,'Date master'!$I:$I),"") -> 17 | H25: =_xlfn.IFNA(_xlfn.XLOOKUP(H26,'Date master'!$E:$E,'Date master'!$I:$I),"") -> 18 | I25: =_xlfn.IFNA(_xlfn.XLOOKUP(I26,'Date master'!$E:$E,'Date master'!$I:$I),"")
C26: =C21+7 -> 45858 | D26: =D21+7 -> 45859 | E26: =E21+7 -> 45860 | F26: =F21+7 -> 45861 | G26: =G21+7 -> 45862 | H26: =H21+7 -> 45863 | I26: =I21+7 -> 45864
C27: {=IFERROR( _xlfn.TEXTJOIN(CHAR(10), TRUE, _xlfn._xlws.FILTER( "- " & 'Commitments & Ownership Matrix'!$B$5:$B$30, ( ( ($I$7="Entire Team") * ('Commitments & Ownership Matrix'!$D$5:$D$30=C25) + (('Commitments & Ownership Matrix'!$F$5:$F$30=$I$7) * ('Commitments & Ownership Matrix'!$D$5:$D$30=C25)) ) * ('Commitments & Ownership Matrix'!$B$5:$B$30 <> "") ) ) ), "" )} | D27: {=IFERROR( _xlfn.TEXTJOIN(CHAR(10), TRUE, _xlfn._xlws.FILTER( "- " & 'Commitments & Ownership Matrix'!$B$5:$B$30, ( ( ($I$7="Entire Team") * ('Commitments & Ownership Matrix'!$D$5:$D$30=D25) + (('Commitments & Ownership Matrix'!$F$5:$F$30=$I$7) * ('Commitments & Ownership Matrix'!$D$5:$D$30=D25)) ) * ('Commitments & Ownership Matrix'!$B$5:$B$30 <> "") ) ) ), "" )} | E27: {=IFERROR( _xlfn.TEXTJOIN(CHAR(10), TRUE, _xlfn._xlws.FILTER( "- " & 'Commitments & Ownership Matrix'!$B$5:$B$30, ( ( ($I$7="Entire Team") * ('Commitments & Ownership Matrix'!$D$5:$D$30=E25) + (('Commitments & Ownership Matrix'!$F$5:$F$30=$I$7) * ('Commitments & Ownership Matrix'!$D$5:$D$30=E25)) ) * ('Commitments & Ownership Matrix'!$B$5:$B$30 <> "") ) ) ), "" )} | F27: {=IFERROR( _xlfn.TEXTJOIN(CHAR(10), TRUE, _xlfn._xlws.FILTER( "- " & 'Commitments & Ownership Matrix'!$B$5:$B$30, ( ( ($I$7="Entire Team") * ('Commitments & Ownership Matrix'!$D$5:$D$30=F25) + (('Commitments & Ownership Matrix'!$F$5:$F$30=$I$7) * ('Commitments & Ownership Matrix'!$D$5:$D$30=F25)) ) * ('Commitments & Ownership Matrix'!$B$5:$B$30 <> "") ) ) ), "" )} | G27: {=IFERROR( _xlfn.TEXTJOIN(CHAR(10), TRUE, _xlfn._xlws.FILTER( "- " & 'Commitments & Ownership Matrix'!$B$5:$B$30, ( ( ($I$7="Entire Team") * ('Commitments & Ownership Matrix'!$D$5:$D$30=G25) + (('Commitments & Ownership Matrix'!$F$5:$F$30=$I$7) * ('Commitments & Ownership Matrix'!$D$5:$D$30=G25)) ) * ('Commitments & Ownership Matrix'!$B$5:$B$30 <> "") ) ) ), "" )} | H27: {=IFERROR( _xlfn.TEXTJOIN(CHAR(10), TRUE, _xlfn._xlws.FILTER( "- " & 'Commitments & Ownership Matrix'!$B$5:$B$30, ( ( ($I$7="Entire Team") * ('Commitments & Ownership Matrix'!$D$5:$D$30=H25) + (('Commitments & Ownership Matrix'!$F$5:$F$30=$I$7) * ('Commitments & Ownership Matrix'!$D$5:$D$30=H25)) ) * ('Commitments & Ownership Matrix'!$B$5:$B$30 <> "") ) ) ), "" )} | I27: {=IFERROR( _xlfn.TEXTJOIN(CHAR(10), TRUE, _xlfn._xlws.FILTER( "- " & 'Commitments & Ownership Matrix'!$B$5:$B$30, ( ( ($I$7="Entire Team") * ('Commitments & Ownership Matrix'!$D$5:$D$30=I25) + (('Commitments & Ownership Matrix'!$F$5:$F$30=$I$7) * ('Commitments & Ownership Matrix'!$D$5:$D$30=I25)) ) * ('Commitments & Ownership Matrix'!$B$5:$B$30 <> "") ) ) ), "" )}
C28: {=IFERROR( _xlfn.TEXTJOIN(CHAR(10), TRUE, _xlfn._xlws.FILTER( "- " & 'Commitments & Ownership Matrix'!$B$5:$B$40, ( (($I$7="Entire Team") * ('Commitments & Ownership Matrix'!$E$5:$E$40=C26)) + (('Commitments & Ownership Matrix'!$F$5:$F$40=$I$7) * ('Commitments & Ownership Matrix'!$E$5:$E$40=C26)) ) * ('Commitments & Ownership Matrix'!$H$5:$H$40="Exceptional") * ('Commitments & Ownership Matrix'!$B$5:$B$40<>"") ) ), "" )} | D28: {=IFERROR( _xlfn.TEXTJOIN(CHAR(10), TRUE, _xlfn._xlws.FILTER( "- " & 'Commitments & Ownership Matrix'!$B$5:$B$40, ( (($I$7="Entire Team") * ('Commitments & Ownership Matrix'!$E$5:$E$40=D26)) + (('Commitments & Ownership Matrix'!$F$5:$F$40=$I$7) * ('Commitments & Ownership Matrix'!$E$5:$E$40=D26)) ) * ('Commitments & Ownership Matrix'!$H$5:$H$40="Exceptional") * ('Commitments & Ownership Matrix'!$B$5:$B$40<>"") ) ), "" )} | E28: {=IFERROR( _xlfn.TEXTJOIN(CHAR(10), TRUE, _xlfn._xlws.FILTER( "- " & 'Commitments & Ownership Matrix'!$B$5:$B$40, ( (($I$7="Entire Team") * ('Commitments & Ownership Matrix'!$E$5:$E$40=E26)) + (('Commitments & Ownership Matrix'!$F$5:$F$40=$I$7) * ('Commitments & Ownership Matrix'!$E$5:$E$40=E26)) ) * ('Commitments & Ownership Matrix'!$H$5:$H$40="Exceptional") * ('Commitments & Ownership Matrix'!$B$5:$B$40<>"") ) ), "" )} | F28: {=IFERROR( _xlfn.TEXTJOIN(CHAR(10), TRUE, _xlfn._xlws.FILTER( "- " & 'Commitments & Ownership Matrix'!$B$5:$B$40, ( (($I$7="Entire Team") * ('Commitments & Ownership Matrix'!$E$5:$E$40=F26)) + (('Commitments & Ownership Matrix'!$F$5:$F$40=$I$7) * ('Commitments & Ownership Matrix'!$E$5:$E$40=F26)) ) * ('Commitments & Ownership Matrix'!$H$5:$H$40="Exceptional") * ('Commitments & Ownership Matrix'!$B$5:$B$40<>"") ) ), "" )} | G28: {=IFERROR( _xlfn.TEXTJOIN(CHAR(10), TRUE, _xlfn._xlws.FILTER( "- " & 'Commitments & Ownership Matrix'!$B$5:$B$40, ( (($I$7="Entire Team") * ('Commitments & Ownership Matrix'!$E$5:$E$40=G26)) + (('Commitments & Ownership Matrix'!$F$5:$F$40=$I$7) * ('Commitments & Ownership Matrix'!$E$5:$E$40=G26)) ) * ('Commitments & Ownership Matrix'!$H$5:$H$40="Exceptional") * ('Commitments & Ownership Matrix'!$B$5:$B$40<>"") ) ), "" )} | H28: {=IFERROR( _xlfn.TEXTJOIN(CHAR(10), TRUE, _xlfn._xlws.FILTER( "- " & 'Commitments & Ownership Matrix'!$B$5:$B$40, ( (($I$7="Entire Team") * ('Commitments & Ownership Matrix'!$E$5:$E$40=H26)) + (('Commitments & Ownership Matrix'!$F$5:$F$40=$I$7) * ('Commitments & Ownership Matrix'!$E$5:$E$40=H26)) ) * ('Commitments & Ownership Matrix'!$H$5:$H$40="Exceptional") * ('Commitments & Ownership Matrix'!$B$5:$B$40<>"") ) ), "" )} | I28: {=IFERROR( _xlfn.TEXTJOIN(CHAR(10), TRUE, _xlfn._xlws.FILTER( "- " & 'Commitments & Ownership Matrix'!$B$5:$B$40, ( (($I$7="Entire Team") * ('Commitments & Ownership Matrix'!$E$5:$E$40=I26)) + (('Commitments & Ownership Matrix'!$F$5:$F$40=$I$7) * ('Commitments & Ownership Matrix'!$E$5:$E$40=I26)) ) * ('Commitments & Ownership Matrix'!$H$5:$H$40="Exceptional") * ('Commitments & Ownership Matrix'!$B$5:$B$40<>"") ) ), "" )}
D29: =_xlfn.XLOOKUP(D26, 'Date master'!$E:$E,'Date master'!$F:$F, "") & " " & _xlfn.XLOOKUP(D26, 'Date master'!$E:$E, 'Date master'!$G:$G, "") | E29: =_xlfn.XLOOKUP(E26, 'Date master'!$E:$E,'Date master'!$F:$F, "") & " " & _xlfn.XLOOKUP(E26, 'Date master'!$E:$E, 'Date master'!$G:$G, "") | F29: =_xlfn.XLOOKUP(F26, 'Date master'!$E:$E,'Date master'!$F:$F, "") & " " & _xlfn.XLOOKUP(F26, 'Date master'!$E:$E, 'Date master'!$G:$G, "") | G29: =_xlfn.XLOOKUP(G26, 'Date master'!$E:$E,'Date master'!$F:$F, "") & " " & _xlfn.XLOOKUP(G26, 'Date master'!$E:$E, 'Date master'!$G:$G, "") | H29: =_xlfn.XLOOKUP(H26, 'Date master'!$E:$E,'Date master'!$F:$F, "") & " " & _xlfn.XLOOKUP(H26, 'Date master'!$E:$E, 'Date master'!$G:$G, "")
C30: =_xlfn.IFNA(_xlfn.XLOOKUP(C31,'Date master'!$E:$E,'Date master'!$I:$I),"") | D30: =_xlfn.IFNA(_xlfn.XLOOKUP(D31,'Date master'!$E:$E,'Date master'!$I:$I),"") -> 19 | E30: =_xlfn.IFNA(_xlfn.XLOOKUP(E31,'Date master'!$E:$E,'Date master'!$I:$I),"") -> 20 | F30: =_xlfn.IFNA(_xlfn.XLOOKUP(F31,'Date master'!$E:$E,'Date master'!$I:$I),"") -> 21 | G30: =_xlfn.IFNA(_xlfn.XLOOKUP(G31,'Date master'!$E:$E,'Date master'!$I:$I),"") -> 22 | H30: =_xlfn.IFNA(_xlfn.XLOOKUP(H31,'Date master'!$E:$E,'Date master'!$I:$I),"") -> 1 | I30: =_xlfn.IFNA(_xlfn.XLOOKUP(I31,'Date master'!$E:$E,'Date master'!$I:$I),"")
C31: =C26+7 -> 45865 | D31: =D26+7 -> 45866 | E31: =E26+7 -> 45867 | F31: =F26+7 -> 45868 | G31: =G26+7 -> 45869 | H31: =H26+7 -> 45870 | I31: =I26+7 -> 45871
C32: {=IFERROR( _xlfn.TEXTJOIN(CHAR(10), TRUE, _xlfn._xlws.FILTER( "- " & 'Commitments & Ownership Matrix'!$B$5:$B$30, ( ( ($I$7="Entire Team") * ('Commitments & Ownership Matrix'!$D$5:$D$30=C30) + (('Commitments & Ownership Matrix'!$F$5:$F$30=$I$7) * ('Commitments & Ownership Matrix'!$D$5:$D$30=C30)) ) * ('Commitments & Ownership Matrix'!$B$5:$B$30 <> "") ) ) ), "" )} | D32: {=IFERROR( _xlfn.TEXTJOIN(CHAR(10), TRUE, _xlfn._xlws.FILTER( "- " & 'Commitments & Ownership Matrix'!$B$5:$B$30, ( ( ($I$7="Entire Team") * ('Commitments & Ownership Matrix'!$D$5:$D$30=D30) + (('Commitments & Ownership Matrix'!$F$5:$F$30=$I$7) * ('Commitments & Ownership Matrix'!$D$5:$D$30=D30)) ) * ('Commitments & Ownership Matrix'!$B$5:$B$30 <> "") ) ) ), "" )} | E32: {=IFERROR( _xlfn.TEXTJOIN(CHAR(10), TRUE, _xlfn._xlws.FILTER( "- " & 'Commitments & Ownership Matrix'!$B$5:$B$30, ( ( ($I$7="Entire Team") * ('Commitments & Ownership Matrix'!$D$5:$D$30=E30) + (('Commitments & Ownership Matrix'!$F$5:$F$30=$I$7) * ('Commitments & Ownership Matrix'!$D$5:$D$30=E30)) ) * ('Commitments & Ownership Matrix'!$B$5:$B$30 <> "") ) ) ), "" )} | F32: {=IFERROR( _xlfn.TEXTJOIN(CHAR(10), TRUE, _xlfn._xlws.FILTER( "- " & 'Commitments & Ownership Matrix'!$B$5:$B$30, ( ( ($I$7="Entire Team") * ('Commitments & Ownership Matrix'!$D$5:$D$30=F30) + (('Commitments & Ownership Matrix'!$F$5:$F$30=$I$7) * ('Commitments & Ownership Matrix'!$D$5:$D$30=F30)) ) * ('Commitments & Ownership Matrix'!$B$5:$B$30 <> "") ) ) ), "" )} | G32: {=IFERROR( _xlfn.TEXTJOIN(CHAR(10), TRUE, _xlfn._xlws.FILTER( "- " & 'Commitments & Ownership Matrix'!$B$5:$B$30, ( ( ($I$7="Entire Team") * ('Commitments & Ownership Matrix'!$D$5:$D$30=G30) + (('Commitments & Ownership Matrix'!$F$5:$F$30=$I$7) * ('Commitments & Ownership Matrix'!$D$5:$D$30=G30)) ) * ('Commitments & Ownership Matrix'!$B$5:$B$30 <> "") ) ) ), "" )} | H32: {=IFERROR( _xlfn.TEXTJOIN(CHAR(10), TRUE, _xlfn._xlws.FILTER( "- " & 'Commitments & Ownership Matrix'!$B$5:$B$30, ( ( ($I$7="Entire Team") * ('Commitments & Ownership Matrix'!$D$5:$D$30=H30) + (('Commitments & Ownership Matrix'!$F$5:$F$30=$I$7) * ('Commitments & Ownership Matrix'!$D$5:$D$30=H30)) ) * ('Commitments & Ownership Matrix'!$B$5:$B$30 <> "") ) ) ), "" )} | I32: {=IFERROR( _xlfn.TEXTJOIN(CHAR(10), TRUE, _xlfn._xlws.FILTER( "- " & 'Commitments & Ownership Matrix'!$B$5:$B$30, ( ( ($I$7="Entire Team") * ('Commitments & Ownership Matrix'!$D$5:$D$30=I30) + (('Commitments & Ownership Matrix'!$F$5:$F$30=$I$7) * ('Commitments & Ownership Matrix'!$D$5:$D$30=I30)) ) * ('Commitments & Ownership Matrix'!$B$5:$B$30 <> "") ) ) ), "" )}
C33: {=IFERROR( _xlfn.TEXTJOIN(CHAR(10), TRUE, _xlfn._xlws.FILTER( "- " & 'Commitments & Ownership Matrix'!$B$5:$B$40, ( (($I$7="Entire Team") * ('Commitments & Ownership Matrix'!$E$5:$E$40=C31)) + (('Commitments & Ownership Matrix'!$F$5:$F$40=$I$7) * ('Commitments & Ownership Matrix'!$E$5:$E$40=C31)) ) * ('Commitments & Ownership Matrix'!$H$5:$H$40="Exceptional") * ('Commitments & Ownership Matrix'!$B$5:$B$40<>"") ) ), "" )} | D33: {=IFERROR( _xlfn.TEXTJOIN(CHAR(10), TRUE, _xlfn._xlws.FILTER( "- " & 'Commitments & Ownership Matrix'!$B$5:$B$40, ( (($I$7="Entire Team") * ('Commitments & Ownership Matrix'!$E$5:$E$40=D31)) + (('Commitments & Ownership Matrix'!$F$5:$F$40=$I$7) * ('Commitments & Ownership Matrix'!$E$5:$E$40=D31)) ) * ('Commitments & Ownership Matrix'!$H$5:$H$40="Exceptional") * ('Commitments & Ownership Matrix'!$B$5:$B$40<>"") ) ), "" )} | E33: {=IFERROR( _xlfn.TEXTJOIN(CHAR(10), TRUE, _xlfn._xlws.FILTER( "- " & 'Commitments & Ownership Matrix'!$B$5:$B$40, ( (($I$7="Entire Team") * ('Commitments & Ownership Matrix'!$E$5:$E$40=E31)) + (('Commitments & Ownership Matrix'!$F$5:$F$40=$I$7) * ('Commitments & Ownership Matrix'!$E$5:$E$40=E31)) ) * ('Commitments & Ownership Matrix'!$H$5:$H$40="Exceptional") * ('Commitments & Ownership Matrix'!$B$5:$B$40<>"") ) ), "" )} | F33: {=IFERROR( _xlfn.TEXTJOIN(CHAR(10), TRUE, _xlfn._xlws.FILTER( "- " & 'Commitments & Ownership Matrix'!$B$5:$B$40, ( (($I$7="Entire Team") * ('Commitments & Ownership Matrix'!$E$5:$E$40=F31)) + (('Commitments & Ownership Matrix'!$F$5:$F$40=$I$7) * ('Commitments & Ownership Matrix'!$E$5:$E$40=F31)) ) * ('Commitments & Ownership Matrix'!$H$5:$H$40="Exceptional") * ('Commitments & Ownership Matrix'!$B$5:$B$40<>"") ) ), "" )} | G33: {=IFERROR( _xlfn.TEXTJOIN(CHAR(10), TRUE, _xlfn._xlws.FILTER( "- " & 'Commitments & Ownership Matrix'!$B$5:$B$40, ( (($I$7="Entire Team") * ('Commitments & Ownership Matrix'!$E$5:$E$40=G31)) + (('Commitments & Ownership Matrix'!$F$5:$F$40=$I$7) * ('Commitments & Ownership Matrix'!$E$5:$E$40=G31)) ) * ('Commitments & Ownership Matrix'!$H$5:$H$40="Exceptional") * ('Commitments & Ownership Matrix'!$B$5:$B$40<>"") ) ), "" )} | H33: {=IFERROR( _xlfn.TEXTJOIN(CHAR(10), TRUE, _xlfn._xlws.FILTER( "- " & 'Commitments & Ownership Matrix'!$B$5:$B$40, ( (($I$7="Entire Team") * ('Commitments & Ownership Matrix'!$E$5:$E$40=H31)) + (('Commitments & Ownership Matrix'!$F$5:$F$40=$I$7) * ('Commitments & Ownership Matrix'!$E$5:$E$40=H31)) ) * ('Commitments & Ownership Matrix'!$H$5:$H$40="Exceptional") * ('Commitments & Ownership Matrix'!$B$5:$B$40<>"") ) ), "" )} | I33: {=IFERROR( _xlfn.TEXTJOIN(CHAR(10), TRUE, _xlfn._xlws.FILTER( "- " & 'Commitments & Ownership Matrix'!$B$5:$B$40, ( (($I$7="Entire Team") * ('Commitments & Ownership Matrix'!$E$5:$E$40=I31)) + (('Commitments & Ownership Matrix'!$F$5:$F$40=$I$7) * ('Commitments & Ownership Matrix'!$E$5:$E$40=I31)) ) * ('Commitments & Ownership Matrix'!$H$5:$H$40="Exceptional") * ('Commitments & Ownership Matrix'!$B$5:$B$40<>"") ) ), "" )}
D34: =_xlfn.XLOOKUP(D31, 'Date master'!$E:$E,'Date master'!$F:$F, "") & " " & _xlfn.XLOOKUP(D31, 'Date master'!$E:$E, 'Date master'!$G:$G, "") | E34: =_xlfn.XLOOKUP(E31, 'Date master'!$E:$E,'Date master'!$F:$F, "") & " " & _xlfn.XLOOKUP(E31, 'Date master'!$E:$E, 'Date master'!$G:$G, "") | F34: =_xlfn.XLOOKUP(F31, 'Date master'!$E:$E,'Date master'!$F:$F, "") & " " & _xlfn.XLOOKUP(F31, 'Date master'!$E:$E, 'Date master'!$G:$G, "") | G34: =_xlfn.XLOOKUP(G31, 'Date master'!$E:$E,'Date master'!$F:$F, "") & " " & _xlfn.XLOOKUP(G31, 'Date master'!$E:$E, 'Date master'!$G:$G, "") | H34: =_xlfn.XLOOKUP(H31, 'Date master'!$E:$E,'Date master'!$F:$F, "") & " " & _xlfn.XLOOKUP(H31, 'Date master'!$E:$E, 'Date master'!$G:$G, "")

Sheet Commitments & Ownership Matrix
B2: Finance Team Recurrig Commitments & Deliverables
B5: Commitments | C5: Start | D5: Deadline | E5: Ad Hoc Deadlines | F5: Main Owner | G5: Audience | H5: Frecuency | I5: Category / Workstream | J5: Priority | K5: Status
B6: Sales close | C6: 1 | D6: 3 | F6: Manager | H6: Recurring | I6: Close & Accounting
B7: Revenue | C7: 1 | D7: 5 | F7: Senior Manager | H7: Exceptional | I7: Close & Accounting
B8: Payroll | C8: 1 | D8: 4 | F8: Payroll Analyst | H8: Recurring | I8: Close & Accounting
B9: Deferred Revenue | C9: 1 | D9: 6 | F9: Senior Analyst | H9: Recurring | I9: Close & Accounting
B10: Unbilled | C10: 4 | D10: 6 | F10: A/P A/R Analyst | H10: Recurring | I10: Close & Accounting
B11: AR Aging | C11: 2 | D11: 5 | F11: A/P A/R Analyst | H11: Recurring | I11: Close & Accounting
B12: Accrued Expenses | C12: 3 | D12: 5 | F12: Finance Manager | H12: Recurring | I12: Close & Accounting
B13: Prepaid Expenses | C13: 5 | D13: 6 | F13: Senior Finance Analyst | H13: Recurring | I13: Close & Accounting
B14: AP Aging | C14: 2 | D14: 5 | F14: A/P A/R Analyst | H14: Recurring | I14: Close & Accounting
B15: Credit Cards | C15: 1 | D15: 5 | F15: Junior Finance Analyst | H15: Recurring | I15: Close & Accounting
B16: Banking | C16: 1 | D16: 6 | F16: Finance Manager | H16: Recurring | I16: Close & Accounting
B17: Mid Close analysis | C17: 3 | D17: 7 | H17: Recurring | I17: Close & Accounting
B18: India Accounting | C18: 1 | D18: 6 | H18: Recurring | I18: Close & Accounting
B19: Intercompany transactions | C19: 6 | D19: 7 | H19: Recurring | I19: Close & Accounting
B20: Final Review | C20: 8 | D20: 8 | H20: Recurring | I20: Close & Accounting
B21: Financial Reporting Package Reporting | C21: 6 | D21: 9 | H21: Recurring | I21: Internal Reporting
B22: Financial Reporting Package Distribution | C22: 10 | D22: 10 | H22: Recurring | I22: Internal Reporting | J22: High
B23: Bank Reporting | C23: 20 | D23: 20 | H23: Recurring | I23: External Reporting | J23: Critical
B24: CEO Report | C24: 15 | D24: 15 | H24: Recurring | I24: Internal Reporting | J24: High
B25: R&D Report | C25: 13 | D25: 13 | H25: Recurring | I25: Internal Reporting
B26: Bank Report | C26: 11 | D26: 11 | H26: Recurring | I26: External Reporting
B27: Board Presentation | C27: 12 | D27: 12 | H27: Recurring | I27: Internal Reporting
B28: Example Special task 1 | C28: N/A | D28: N/A | E28: 45845 | H28: Exceptional | I28: Projects / Strategic Initiatives
B29: Example Special task 2 | C29: N/A | D29: N/A | E29: 7/232025 | H29: Exceptional | I29: Projects / Strategic Initiatives
B30: Example Special task 3 | C30: N/A | D30: N/A | E30: 45856 | H30: Exceptional | I30: Projects / Strategic Initiatives
B31: 2023 Audit Related example 1 | C31: N/A | D31: N/A | E31: 45852 | H31: Exceptional | I31: Compliance / Audit
B32: 2023 Audit Related example 2 | C32: N/A | D32: N/A | E32: 45860 | H32: Exceptional | I32: Compliance / Audit
B33: 2023 Audit Related example 3 | C33: N/A | D33: N/A | E33: 45866 | H33: Exceptional | I33: Compliance / Audit
B34: 2023 Audit Related example 4 | C34: N/A | D34: N/A | E34: 45840 | H34: Exceptional | I34: Compliance / Audit

Sheet Detailed Tasks
B2: Finance Team Commitments & Deliverables breakdown details
I4: Team Involved (alphabetical order)
B5: Commitments | C5: Detailed Task | D5: Start | E5: Deadline | F5: Ad Hoc Deadlines | G5: Main Owner | H5: Audience | I5: Team Member 1 | J5: Team Member 2 | K5: Team Member 3 | L5: Team Member 4 | M5: Team Member 5 | N5: Team Member 6 | O5: Team Member 7 | P5: Team Member 8 | Q5: Team Member 9 | R5: Frecuency | S5: Category / Workstream | T5: Priority | U5: Status
B6: Sales close | C6: =Table3[[#This Row],[Commitments]] -> Sales close | D6: 1 | E6: 3 | I6: No | J6: No | K6: No | L6: No | M6: No | N6: No | O6: No | P6: No | Q6: No | R6: Recurring | S6: Close & Accounting
B7: Revenue | C7: Existing MRR | D7: 1 | E7: 1 | I7: No | J7: No | K7: No | L7: No | M7: Yes | N7: Yes | O7: No | P7: No | Q7: No | R7: Recurring | S7: Close & Accounting
B8: Revenue | C8: New business | D8: 4 | E8: 4 | I8: Yes | J8: No | K8: No | L8: No | M8: Yes | N8: Yes | O8: No | P8: No | Q8: No | R8: Recurring
B9: Revenue | C9: Variable Fees | D9: 4 | E9: 4 | I9: No | J9: No | K9: No | L9: No | M9: Yes | N9: Yes | O9: No | P9: No | Q9: No | R9: Recurring
B10: Revenue | C10: Meeting to review monthly revenue | D10: 5 | E10: 5 | I10: Yes | J10: No | K10: No | L10: Yes | M10: Yes | N10: Yes | O10: No | P10: No | Q10: No | R10: Recurring
B11: Revenue | C11: Finalize | D11: 5 | E11: 5 | I11: Yes | J11: No | K11: No | L11: Yes | M11: Yes | N11: Yes | O11: No | P11: No | Q11: No | R11: Recurring
B12: Payroll | C12: Download Code payroll files | D12: 1 | E12: 1 | I12: Yes | J12: No | K12: No | L12: No | M12: No | N12: No | O12: No | P12: No | Q12: Yes | R12: Recurring | S12: Payroll | T12: High
B13: Payroll | C13: Book payroll | D13: 2 | E13: 2 | I13: No | J13: No | K13: No | L13: No | M13: No | N13: No | O13: No | P13: No | Q13: Yes | R13: Recurring | S13: Payroll | T13: High
B14: Payroll | C14: Reconciled payroll expense booked to payroll reports | D14: 3 | E14: 3 | I14: No | J14: No | K14: No | L14: No | M14: No | N14: No | O14: Yes | P14: No | Q14: Yes | R14: Recurring | S14: Payroll | T14: High
B15: Payroll | C15: Meeting to review payroll JE's through GL (P&L & BS) | D15: 4 | E15: 4 | I15: Yes | J15: No | K15: No | L15: Yes | M15: No | N15: No | O15: No | P15: No | Q15: Yes | R15: Recurring | S15: Payroll | T15: High
B16: Deferred Revenue | C16: Finalize | D16: 4 | E16: 4 | I16: Yes | J16: No | K16: No | L16: Yes | M16: Yes | N16: Yes | O16: No | P16: No | Q16: No | R16: Recurring
B17: Deferred Revenue | C17: Generate & distribute Deferred Revenue Detail Schedule, must tie to the BS by subsidiary | D17: 5 | E17: 5 | I17: No | J17: No | K17: No | L17: No | M17: Yes | N17: Yes | O17: No | P17: No | Q17: No | R17: Recurring
B18: Deferred Revenue | C18: Meeting to review Deferred Revenue Detail Schedule | D18: 6 | E18: 6 | I18: Yes | J18: No | K18: No | L18: Yes | M18: Yes | N18: Yes | O18: No | P18: No | Q18: No | R18: Recurring
B19: Unbilled | C19: New business | D19: 4 | E19: 4 | I19: Yes | J19: No | K19: No | L19: No | M19: Yes | N19: Yes | O19: No | P19: No | Q19: No | R19: Recurring
B20: Unbilled | C20: Variable Fees | D20: 4 | E20: 4 | I20: No | J20: No | K20: No | L20: No | M20: Yes | N20: Yes | O20: No | P20: No | Q20: No | R20: Recurring
B21: Unbilled | C21: Finalize | D21: 4 | E21: 4 | I21: Yes | J21: No | K21: No | L21: No | M21: Yes | N21: Yes | O21: No | P21: No | Q21: No | R21: Recurring
B22: Unbilled | C22: Generate & distribute Unbilled Revenue Detail Schedule, must tie to the BS by subsidiary | D22: 5 | E22: 5 | I22: No | J22: No | K22: No | L22: No | M22: Yes | N22: Yes | O22: No | P22: No | Q22: No | R22: Recurring
B23: Unbilled | C23: Meeting to review Unbilled Revenue Detail Schedule | D23: 6 | E23: 6 | I23: Yes | J23: No | K23: No | L23: Yes | M23: Yes | N23: Yes | O23: No | P23: No | Q23: No | R23: Recurring
B24: AR Aging | C24: Ensure all payments are posted in NS | D24: 2 | E24: 2 | I24: No | J24: No | K24: No | L24: No | M24: Yes | N24: Yes | O24: No | P24: No | Q24: No | R24: Recurring | S24: Cash & Treasury
B25: AR Aging | C25: Clean up aging to eliminate negative balances | D25: 3 | E25: 3 | I25: No | J25: No | K25: No | L25: No | M25: Yes | N25: Yes | O25: No | P25: No | Q25: No | R25: Recurring | S25: Cash & Treasury
B26: AR Aging | C26: Run & Save AR Aging in month end folder on One Drive | D26: 3 | E26: 3 | I26: No | J26: No | K26: No | L26: No | M26: Yes | N26: Yes | O26: No | P26: No | Q26: No | R26: Recurring | S26: Cash & Treasury
B27: AR Aging | C27: Meeting to review AR Aging | D27: 4 | E27: 5 | I27: Yes | J27: No | K27: No | L27: Yes | M27: Yes | N27: Yes | O27: No | P27: No | Q27: No | R27: Recurring | S27: Cash & Treasury
B28: AR Aging | C28: A/R Report by Delivery Function | D28: 4 | E28: 5 | I28: Yes | J28: No | K28: No | L28: Yes | M28: Yes | N28: Yes | O28: Yes | P28: No | Q28: No | R28: Recurring | S28: Cash & Treasury
B29: Accrued Expenses | C29: Maintain monthly accrued expenses | D29: 3 | E29: 3 | I29: No | J29: No | K29: No | L29: No | M29: No | N29: No | O29: No | P29: No | Q29: No | R29: Recurring
B30: Accrued Expenses | C30: Generate & distribute Accrued Expense Detail Schedule, must tie to the BS by subsidiary | D30: 4 | E30: 4 | I30: No | J30: No | K30: No | L30: No | M30: No | N30: No | O30: No | P30: No | Q30: No | R30: Recurring
B31: Accrued Expenses | C31: Meeting to review acrued expenses and month-over-months movements | D31: 5 | E31: 5 | I31: No | J31: No | K31: No | L31: No | M31: No | N31: No | O31: No | P31: No | Q31: No | R31: Recurring
B32: Prepaid Expenses | C32: Maintain monthly prepaid expenses | D32: 5 | E32: 5 | I32: No | J32: No | K32: No | L32: No | M32: No | N32: No | O32: No | P32: No | Q32: No | R32: Recurring
B33: Prepaid Expenses | C33: Generate & distribute Prepaid Expense Detail Schedule, must tie to the BS by subsidiary | D33: 6 | E33: 6 | I33: No | J33: No | K33: No | L33: No | M33: No | N33: No | O33: No | P33: No | Q33: No | R33: Recurring
B34: Prepaid Expenses | C34: Meeting to review Prepaid Expenses and month-over-months movements | D34: 6 | E34: 6 | I34: No | J34: No | K34: No | L34: No | M34: No | N34: No | O34: No | P34: No | Q34: No | R34: Recurring
B35: AP Aging | C35: Ensure all payments are posted in NS | D35: 2 | E35: 2 | I35: No | J35: No | K35: No | L35: No | M35: No | N35: No | O35: No | P35: No | Q35: No | R35: Recurring
B36: AP Aging | C36: Clean up aging to eliminate negative balances | D36: 3 | E36: 3 | I36: No | J36: No | K36: No | L36: No | M36: No | N36: No | O36: No | P36: No | Q36: No | R36: Recurring
B37: AP Aging | C37: Run & Save AP Aging in month end folder on Egnyte | D37: 3 | E37: 3 | I37: No | J37: No | K37: No | L37: No | M37: No | N37: No | O37: No | P37: No | Q37: No | R37: Recurring
B38: AP Aging | C38: Meeting to review AP Aging | D38: 5 | E38: 5 | I38: No | J38: No | K38: No | L38: No | M38: No | N38: No | O38: No | P38: No | Q38: No | R38: Recurring
B39: Credit Cards | C39: Download credit reports | D39: 1 | E39: 1 | I39: No | J39: No | K39: No | L39: No | M39: No | N39: No | O39: No | P39: No | Q39: No | R39: Recurring
B40: Credit Cards | C40: Reconcile & process | D40: 5 | E40: 5 | I40: No | J40: No | K40: No | L40: No | M40: No | N40: No | O40: No | P40: No | Q40: No | R40: Recurring
... B49: Financial Reporting Package Final Review | C49: Final review and adjusting entries | D49: 8 | E49: 8 | I49: No | J49: No | K49: No | L49: No | M49: No | N49: No | O49: No | P49: No | Q49: No | R49: Recurring
B50: Financial Reporting Package Reporting | C50: Prep of Financial Reporting Package & Work Copy | D50: 6 | E50: 9 | H50: Director / cfo | I50: No | J50: No | K50: No | L50: No | M50: No | N50: No | O50: No | P50: No | Q50: No | R50: Recurring
B51: Financial Reporting Package Distribution | D51: 10 | E51: 10 | H51: CEO / SLT | I51: No | J51: No | K51: No | L51: No | M51: No | N51: No | O51: No | P51: No | Q51: No | R51: Recurring
B52: Bank Reporting | D52: 20 | E52: 20 | H52: cfo / Bank Bank | I52: No | J52: No | K52: No | L52: No | M52: No | N52: No | O52: No | P52: No | Q52: No | R52: Recurring
B53: CEO Report | D53: 15 | E53: 15 | H53: CEO | I53: No | J53: No | K53: No | L53: No | M53: No | N53: No | O53: No | P53: No | Q53: No | R53: Recurring
B54: R&D Report for CTO | D54: 13 | E54: 13 | H54: CTO | I54: No | J54: No | K54: No | L54: No | M54: No | N54: No | O54: No | P54: No | Q54: No | R54: Recurring | S54: Internal Reporting
B55: Board Report | D55: 11 | E55: 11 | H55: Board Member | I55: No | J55: No | K55: No | L55: No | M55: No | N55: No | O55: No | P55: No | Q55: No | R55: Recurring | S55: External Reporting
B56: Board Presentation | D56: 12 | E56: 12 | I56: No | J56: No | K56: No | L56: No | M56: No | N56: No | O56: No | P56: No | Q56: No | R56: Recurring | S56: Internal Reporting
B57: Example Special task 1 | D57: N/A | E57: N/A | F57: 45845 | I57: No | J57: No | K57: No | L57: No | M57: No | N57: No | O57: No | P57: No | Q57: No | R57: Exceptional
B58: Example Special task 2 | D58: N/A | E58: N/A | F58: 7/232025 | I58: No | J58: No | K58: No | L58: No | M58: No | N58: No | O58: No | P58: No | Q58: No | R58: Exceptional
B59: Example Special task 3 | D59: N/A | E59: N/A | F59: 45856 | I59: No | J59: No | K59: No | L59: No | M59: No | N59: No | O59: No | P59: No | Q59: No | R59: Exceptional
B60: 2023 Audit Related example 1 | D60: N/A | E60: N/A | F60: 45852 | I60: No | J60: No | K60: No | L60: No | M60: No | N60: No | O60: No | P60: No | Q60: No | R60: Exceptional
B61: 2024 Audit Related example 2 | D61: N/A | E61: N/A | F61: 45860 | I61: No | J61: No | K61: No | L61: No | M61: No | N61: No | O61: No | P61: No | Q61: No | R61: Exceptional
B62: 2025 Audit Related example 3 | D62: N/A | E62: N/A | F62: 45866 | I62: No | J62: No | K62: No | L62: No | M62: No | N62: No | O62: No | P62: No | Q62: No | R62: Exceptional
B63: 2026 Audit Related example 4 | D63: N/A | E63: N/A | F63: 45840 | I63: No | J63: No | K63: No | L63: No | M63: No | N63: No | O63: No | P63: No | Q63: No | R63: Exceptional

Sheet Schedules>>

Sheet Date master
B1: Year | C1: Month | D1: Weekday | E1: Date | F1: US Holiday | G1: India Holiday | H1: Holiday? | I1: Finance day
B2: =YEAR(E2) -> 2025 | C2: =TEXT(E2,"mmmm") -> July | D2: =TEXT(E2,"dddd") -> Tuesday | E2: 45839 | H2: =IF(OR(Table1[[#This Row],[US Holiday]]<>"", Table1[[#This Row],[India Holiday]]<>""), "Yes", "No") -> No | I2: 1
B3: =YEAR(E3) -> 2025 | C3: =TEXT(E3,"mmmm") -> July | D3: =TEXT(E3,"dddd") -> Wednesday | E3: 45840 | H3: =IF(OR(Table1[[#This Row],[US Holiday]]<>"", Table1[[#This Row],[India Holiday]]<>""), "Yes", "No") -> No | I3: =IF( AND( WORKDAY(E3-1,1)=E3, _xlfn.CONCAT(F3:G3)="" ), _xlfn.MAXIFS(I$2:I2,C$2:C2,C3,B$2:B2,B3)+1, "" ) -> 2
B4: =YEAR(E4) -> 2025 | C4: =TEXT(E4,"mmmm") -> July | D4: =TEXT(E4,"dddd") -> Thursday | E4: 45841 | H4: =IF(OR(Table1[[#This Row],[US Holiday]]<>"", Table1[[#This Row],[India Holiday]]<>""), "Yes", "No") -> No | I4: =IF( AND( WORKDAY(E4-1,1)=E4, _xlfn.CONCAT(F4:G4)="" ), _xlfn.MAXIFS(I$2:I3,C$2:C3,C4,B$2:B3,B4)+1, "" ) -> 3
B5: =YEAR(E5) -> 2025 | C5: =TEXT(E5,"mmmm") -> July | D5: =TEXT(E5,"dddd") -> Friday | E5: 45842 | F5: US Independence Day | H5: =IF(OR(Table1[[#This Row],[US Holiday]]<>"", Table1[[#This Row],[India Holiday]]<>""), "Yes", "No") -> Yes | I5: =IF( AND( WORKDAY(E5-1,1)=E5, _xlfn.CONCAT(F5:G5)="" ), _xlfn.MAXIFS(I$2:I4,C$2:C4,C5,B$2:B4,B5)+1, "" )
B6: =YEAR(E6) -> 2025 | C6: =TEXT(E6,"mmmm") -> July | D6: =TEXT(E6,"dddd") -> Saturday | E6: 45843 | H6: =IF(OR(Table1[[#This Row],[US Holiday]]<>"", Table1[[#This Row],[India Holiday]]<>""), "Yes", "No") -> No | I6: =IF( AND( WORKDAY(E6-1,1)=E6, _xlfn.CONCAT(F6:G6)="" ), _xlfn.MAXIFS(I$2:I5,C$2:C5,C6,B$2:B5,B6)+1, "" )
B7: =YEAR(E7) -> 2025 | C7: =TEXT(E7,"mmmm") -> July | D7: =TEXT(E7,"dddd") -> Sunday | E7: 45844 | H7: =IF(OR(Table1[[#This Row],[US Holiday]]<>"", Table1[[#This Row],[India Holiday]]<>""), "Yes", "No") -> No | I7: =IF( AND( WORKDAY(E7-1,1)=E7, _xlfn.CONCAT(F7:G7)="" ), _xlfn.MAXIFS(I$2:I6,C$2:C6,C7,B$2:B6,B7)+1, "" )
B8: =YEAR(E8) -> 2025 | C8: =TEXT(E8,"mmmm") -> July | D8: =TEXT(E8,"dddd") -> Monday | E8: 45845 | H8: =IF(OR(Table1[[#This Row],[US Holiday]]<>"", Table1[[#This Row],[India Holiday]]<>""), "Yes", "No") -> No | I8: =IF( AND( WORKDAY(E8-1,1)=E8, _xlfn.CONCAT(F8:G8)="" ), _xlfn.MAXIFS(I$2:I7,C$2:C7,C8,B$2:B7,B8)+1, "" ) -> 4
B9: =YEAR(E9) -> 2025 | C9: =TEXT(E9,"mmmm") -> July | D9: =TEXT(E9,"dddd") -> Tuesday | E9: 45846 | H9: =IF(OR(Table1[[#This Row],[US Holiday]]<>"", Table1[[#This Row],[India Holiday]]<>""), "Yes", "No") -> No | I9: =IF( AND( WORKDAY(E9-1,1)=E9, _xlfn.CONCAT(F9:G9)="" ), _xlfn.MAXIFS(I$2:I8,C$2:C8,C9,B$2:B8,B9)+1, "" ) -> 5
B10: =YEAR(E10) -> 2025 | C10: =TEXT(E10,"mmmm") -> July | D10: =TEXT(E10,"dddd") -> Wednesday | E10: 45847 | H10: =IF(OR(Table1[[#This Row],[US Holiday]]<>"", Table1[[#This Row],[India Holiday]]<>""), "Yes", "No") -> No | I10: =IF( AND( WORKDAY(E10-1,1)=E10, _xlfn.CONCAT(F10:G10)="" ), _xlfn.MAXIFS(I$2:I9,C$2:C9,C10,B$2:B9,B10)+1, "" ) -> 6
B11: =YEAR(E11) -> 2025 | C11: =TEXT(E11,"mmmm") -> July | D11: =TEXT(E11,"dddd") -> Thursday | E11: 45848 | H11: =IF(OR(Table1[[#This Row],[US Holiday]]<>"", Table1[[#This Row],[India Holiday]]<>""), "Yes", "No") -> No | I11: =IF( AND( WORKDAY(E11-1,1)=E11, _xlfn.CONCAT(F11:G11)="" ), _xlfn.MAXIFS(I$2:I10,C$2:C10,C11,B$2:B10,B11)+1, "" ) -> 7
B12: =YEAR(E12) -> 2025 | C12: =TEXT(E12,"mmmm") -> July | D12: =TEXT(E12,"dddd") -> Friday | E12: 45849 | H12: =IF(OR(Table1[[#This Row],[US Holiday]]<>"", Table1[[#This Row],[India Holiday]]<>""), "Yes", "No") -> No | I12: =IF( AND( WORKDAY(E12-1,1)=E12, _xlfn.CONCAT(F12:G12)="" ), _xlfn.MAXIFS(I$2:I11,C$2:C11,C12,B$2:B11,B12)+1, "" ) -> 8
B13: =YEAR(E13) -> 2025 | C13: =TEXT(E13,"mmmm") -> July | D13: =TEXT(E13,"dddd") -> Saturday | E13: 45850 | H13: =IF(OR(Table1[[#This Row],[US Holiday]]<>"", Table1[[#This Row],[India Holiday]]<>""), "Yes", "No") -> No | I13: =IF( AND( WORKDAY(E13-1,1)=E13, _xlfn.CONCAT(F13:G13)="" ), _xlfn.MAXIFS(I$2:I12,C$2:C12,C13,B$2:B12,B13)+1, "" )
B14: =YEAR(E14) -> 2025 | C14: =TEXT(E14,"mmmm") -> July | D14: =TEXT(E14,"dddd") -> Sunday | E14: 45851 | H14: =IF(OR(Table1[[#This Row],[US Holiday]]<>"", Table1[[#This Row],[India Holiday]]<>""), "Yes", "No") -> No | I14: =IF( AND( WORKDAY(E14-1,1)=E14, _xlfn.CONCAT(F14:G14)="" ), _xlfn.MAXIFS(I$2:I13,C$2:C13,C14,B$2:B13,B14)+1, "" )
B15: =YEAR(E15) -> 2025 | C15: =TEXT(E15,"mmmm") -> July | D15: =TEXT(E15,"dddd") -> Monday | E15: 45852 | H15: =IF(OR(Table1[[#This Row],[US Holiday]]<>"", Table1[[#This Row],[India Holiday]]<>""), "Yes", "No") -> No | I15: =IF( AND( WORKDAY(E15-1,1)=E15, _xlfn.CONCAT(F15:G15)="" ), _xlfn.MAXIFS(I$2:I14,C$2:C14,C15,B$2:B14,B15)+1, "" ) -> 9
B16: =YEAR(E16) -> 2025 | C16: =TEXT(E16,"mmmm") -> July | D16: =TEXT(E16,"dddd") -> Tuesday | E16: 45853 | H16: =IF(OR(Table1[[#This Row],[US Holiday]]<>"", Table1[[#This Row],[India Holiday]]<>""), "Yes", "No") -> No | I16: =IF( AND( WORKDAY(E16-1,1)=E16, _xlfn.CONCAT(F16:G16)="" ), _xlfn.MAXIFS(I$2:I15,C$2:C15,C16,B$2:B15,B16)+1, "" ) -> 10
B17: =YEAR(E17) -> 2025 | C17: =TEXT(E17,"mmmm") -> July | D17: =TEXT(E17,"dddd") -> Wednesday | E17: 45854 | H17: =IF(OR(Table1[[#This Row],[US Holiday]]<>"", Table1[[#This Row],[India Holiday]]<>""), "Yes", "No") -> No | I17: =IF( AND( WORKDAY(E17-1,1)=E17, _xlfn.CONCAT(F17:G17)="" ), _xlfn.MAXIFS(I$2:I16,C$2:C16,C17,B$2:B16,B17)+1, "" ) -> 11
... B46: =YEAR(E46) -> 2025 | C46: =TEXT(E46,"mmmm") -> August | D46: =TEXT(E46,"dddd") -> Thursday | E46: 45883 | H46: =IF(OR(Table1[[#This Row],[US Holiday]]<>"", Table1[[#This Row],[India Holiday]]<>""), "Yes", "No") -> No | I46: =IF( AND( WORKDAY(E46-1,1)=E46, _xlfn.CONCAT(F46:G46)="" ), _xlfn.MAXIFS(I$2:I45,C$2:C45,C46,B$2:B45,B46)+1, "" ) -> 10
B47: =YEAR(E47) -> 2025 | C47: =TEXT(E47,"mmmm") -> August | D47: =TEXT(E47,"dddd") -> Friday | E47: 45884 | G47: India Independence Day | H47: =IF(OR(Table1[[#This Row],[US Holiday]]<>"", Table1[[#This Row],[India Holiday]]<>""), "Yes", "No") -> Yes | I47: =IF( AND( WORKDAY(E47-1,1)=E47, _xlfn.CONCAT(F47:G47)="" ), _xlfn.MAXIFS(I$2:I46,C$2:C46,C47,B$2:B46,B47)+1, "" )
B48: =YEAR(E48) -> 2025 | C48: =TEXT(E48,"mmmm") -> August | D48: =TEXT(E48,"dddd") -> Saturday | E48: 45885 | H48: =IF(OR(Table1[[#This Row],[US Holiday]]<>"", Table1[[#This Row],[India Holiday]]<>""), "Yes", "No") -> No | I48: =IF( AND( WORKDAY(E48-1,1)=E48, _xlfn.CONCAT(F48:G48)="" ), _xlfn.MAXIFS(I$2:I47,C$2:C47,C48,B$2:B47,B48)+1, "" )
B49: =YEAR(E49) -> 2025 | C49: =TEXT(E49,"mmmm") -> August | D49: =TEXT(E49,"dddd") -> Sunday | E49: 45886 | H49: =IF(OR(Table1[[#This Row],[US Holiday]]<>"", Table1[[#This Row],[India Holiday]]<>""), "Yes", "No") -> No | I49: =IF( AND( WORKDAY(E49-1,1)=E49, _xlfn.CONCAT(F49:G49)="" ), _xlfn.MAXIFS(I$2:I48,C$2:C48,C49,B$2:B48,B49)+1, "" )
B50: =YEAR(E50) -> 2025 | C50: =TEXT(E50,"mmmm") -> August | D50: =TEXT(E50,"dddd") -> Monday | E50: 45887 | H50: =IF(OR(Table1[[#This Row],[US Holiday]]<>"", Table1[[#This Row],[India Holiday]]<>""), "Yes", "No") -> No | I50: =IF( AND( WORKDAY(E50-1,1)=E50, _xlfn.CONCAT(F50:G50)="" ), _xlfn.MAXIFS(I$2:I49,C$2:C49,C50,B$2:B49,B50)+1, "" ) -> 11
B51: =YEAR(E51) -> 2025 | C51: =TEXT(E51,"mmmm") -> August | D51: =TEXT(E51,"dddd") -> Tuesday | E51: 45888 | H51: =IF(OR(Table1[[#This Row],[US Holiday]]<>"", Table1[[#This Row],[India Holiday]]<>""), "Yes", "No") -> No | I51: =IF( AND( WORKDAY(E51-1,1)=E51, _xlfn.CONCAT(F51:G51)="" ), _xlfn.MAXIFS(I$2:I50,C$2:C50,C51,B$2:B50,B51)+1, "" ) -> 12
B52: =YEAR(E52) -> 2025 | C52: =TEXT(E52,"mmmm") -> August | D52: =TEXT(E52,"dddd") -> Wednesday | E52: 45889 | H52: =IF(OR(Table1[[#This Row],[US Holiday]]<>"", Table1[[#This Row],[India Holiday]]<>""), "Yes", "No") -> No | I52: =IF( AND( WORKDAY(E52-1,1)=E52, _xlfn.CONCAT(F52:G52)="" ), _xlfn.MAXIFS(I$2:I51,C$2:C51,C52,B$2:B51,B52)+1, "" ) -> 13
B53: =YEAR(E53) -> 2025 | C53: =TEXT(E53,"mmmm") -> August | D53: =TEXT(E53,"dddd") -> Thursday | E53: 45890 | H53: =IF(OR(Table1[[#This Row],[US Holiday]]<>"", Table1[[#This Row],[India Holiday]]<>""), "Yes", "No") -> No | I53: =IF( AND( WORKDAY(E53-1,1)=E53, _xlfn.CONCAT(F53:G53)="" ), _xlfn.MAXIFS(I$2:I52,C$2:C52,C53,B$2:B52,B53)+1, "" ) -> 14
B54: =YEAR(E54) -> 2025 | C54: =TEXT(E54,"mmmm") -> August | D54: =TEXT(E54,"dddd") -> Friday | E54: 45891 | H54: =IF(OR(Table1[[#This Row],[US Holiday]]<>"", Table1[[#This Row],[India Holiday]]<>""), "Yes", "No") -> No | I54: =IF( AND( WORKDAY(E54-1,1)=E54, _xlfn.CONCAT(F54:G54)="" ), _xlfn.MAXIFS(I$2:I53,C$2:C53,C54,B$2:B53,B54)+1, "" ) -> 15
B55: =YEAR(E55) -> 2025 | C55: =TEXT(E55,"mmmm") -> August | D55: =TEXT(E55,"dddd") -> Saturday | E55: 45892 | H55: =IF(OR(Table1[[#This Row],[US Holiday]]<>"", Table1[[#This Row],[India Holiday]]<>""), "Yes", "No") -> No | I55: =IF( AND( WORKDAY(E55-1,1)=E55, _xlfn.CONCAT(F55:G55)="" ), _xlfn.MAXIFS(I$2:I54,C$2:C54,C55,B$2:B54,B55)+1, "" )
B56: =YEAR(E56) -> 2025 | C56: =TEXT(E56,"mmmm") -> August | D56: =TEXT(E56,"dddd") -> Sunday | E56: 45893 | H56: =IF(OR(Table1[[#This Row],[US Holiday]]<>"", Table1[[#This Row],[India Holiday]]<>""), "Yes", "No") -> No | I56: =IF( AND( WORKDAY(E56-1,1)=E56, _xlfn.CONCAT(F56:G56)="" ), _xlfn.MAXIFS(I$2:I55,C$2:C55,C56,B$2:B55,B56)+1, "" )
B57: =YEAR(E57) -> 2025 | C57: =TEXT(E57,"mmmm") -> August | D57: =TEXT(E57,"dddd") -> Monday | E57: 45894 | H57: =IF(OR(Table1[[#This Row],[US Holiday]]<>"", Table1[[#This Row],[India Holiday]]<>""), "Yes", "No") -> No | I57: =IF( AND( WORKDAY(E57-1,1)=E57, _xlfn.CONCAT(F57:G57)="" ), _xlfn.MAXIFS(I$2:I56,C$2:C56,C57,B$2:B56,B57)+1, "" ) -> 16
B58: =YEAR(E58) -> 2025 | C58: =TEXT(E58,"mmmm") -> August | D58: =TEXT(E58,"dddd") -> Tuesday | E58: 45895 | H58: =IF(OR(Table1[[#This Row],[US Holiday]]<>"", Table1[[#This Row],[India Holiday]]<>""), "Yes", "No") -> No | I58: =IF( AND( WORKDAY(E58-1,1)=E58, _xlfn.CONCAT(F58:G58)="" ), _xlfn.MAXIFS(I$2:I57,C$2:C57,C58,B$2:B57,B58)+1, "" ) -> 17
B59: =YEAR(E59) -> 2025 | C59: =TEXT(E59,"mmmm") -> August | D59: =TEXT(E59,"dddd") -> Wednesday | E59: 45896 | H59: =IF(OR(Table1[[#This Row],[US Holiday]]<>"", Table1[[#This Row],[India Holiday]]<>""), "Yes", "No") -> No | I59: =IF( AND( WORKDAY(E59-1,1)=E59, _xlfn.CONCAT(F59:G59)="" ), _xlfn.MAXIFS(I$2:I58,C$2:C58,C59,B$2:B58,B59)+1, "" ) -> 18
... B63: =YEAR(E63) -> 2025 | C63: =TEXT(E63,"mmmm") -> August | D63: =TEXT(E63,"dddd") -> Sunday | E63: 45900 | H63: =IF(OR(Table1[[#This Row],[US Holiday]]<>"", Table1[[#This Row],[India Holiday]]<>""), "Yes", "No") -> No | I63: =IF( AND( WORKDAY(E63-1,1)=E63, _xlfn.CONCAT(F63:G63)="" ), _xlfn.MAXIFS(I$2:I62,C$2:C62,C63,B$2:B62,B63)+1, "" )
B64: =YEAR(E64) -> 2025 | C64: =TEXT(E64,"mmmm") -> September | D64: =TEXT(E64,"dddd") -> Monday | E64: 45901 | F64: Labor Day | H64: =IF(OR(Table1[[#This Row],[US Holiday]]<>"", Table1[[#This Row],[India Holiday]]<>""), "Yes", "No") -> Yes | I64: =IF( AND( WORKDAY(E64-1,1)=E64, _xlfn.CONCAT(F64:G64)="" ), _xlfn.MAXIFS(I$2:I63,C$2:C63,C64,B$2:B63,B64)+1, "" )
B65: =YEAR(E65) -> 2025 | C65: =TEXT(E65,"mmmm") -> September | D65: =TEXT(E65,"dddd") -> Tuesday | E65: 45902 | H65: =IF(OR(Table1[[#This Row],[US Holiday]]<>"", Table1[[#This Row],[India Holiday]]<>""), "Yes", "No") -> No | I65: =IF( AND( WORKDAY(E65-1,1)=E65, _xlfn.CONCAT(F65:G65)="" ), _xlfn.MAXIFS(I$2:I64,C$2:C64,C65,B$2:B64,B65)+1, "" ) -> 1
B66: =YEAR(E66) -> 2025 | C66: =TEXT(E66,"mmmm") -> September | D66: =TEXT(E66,"dddd") -> Wednesday | E66: 45903 | H66: =IF(OR(Table1[[#This Row],[US Holiday]]<>"", Table1[[#This Row],[India Holiday]]<>""), "Yes", "No") -> No | I66: =IF( AND( WORKDAY(E66-1,1)=E66, _xlfn.CONCAT(F66:G66)="" ), _xlfn.MAXIFS(I$2:I65,C$2:C65,C66,B$2:B65,B66)+1, "" ) -> 2
B67: =YEAR(E67) -> 2025 | C67: =TEXT(E67,"mmmm") -> September | D67: =TEXT(E67,"dddd") -> Thursday | E67: 45904 | H67: =IF(OR(Table1[[#This Row],[US Holiday]]<>"", Table1[[#This Row],[India Holiday]]<>""), "Yes", "No") -> No | I67: =IF( AND( WORKDAY(E67-1,1)=E67, _xlfn.CONCAT(F67:G67)="" ), _xlfn.MAXIFS(I$2:I66,C$2:C66,C67,B$2:B66,B67)+1, "" ) -> 3
B68: =YEAR(E68) -> 2025 | C68: =TEXT(E68,"mmmm") -> September | D68: =TEXT(E68,"dddd") -> Friday | E68: 45905 | H68: =IF(OR(Table1[[#This Row],[US Holiday]]<>"", Table1[[#This Row],[India Holiday]]<>""), "Yes", "No") -> No | I68: =IF( AND( WORKDAY(E68-1,1)=E68, _xlfn.CONCAT(F68:G68)="" ), _xlfn.MAXIFS(I$2:I67,C$2:C67,C68,B$2:B67,B68)+1, "" ) -> 4
B69: =YEAR(E69) -> 2025 | C69: =TEXT(E69,"mmmm") -> September | D69: =TEXT(E69,"dddd") -> Saturday | E69: 45906 | H69: =IF(OR(Table1[[#This Row],[US Holiday]]<>"", Table1[[#This Row],[India Holiday]]<>""), "Yes", "No") -> No | I69: =IF( AND( WORKDAY(E69-1,1)=E69, _xlfn.CONCAT(F69:G69)="" ), _xlfn.MAXIFS(I$2:I68,C$2:C68,C69,B$2:B68,B69)+1, "" )
B70: =YEAR(E70) -> 2025 | C70: =TEXT(E70,"mmmm") -> September | D70: =TEXT(E70,"dddd") -> Sunday | E70: 45907 | H70: =IF(OR(Table1[[#This Row],[US Holiday]]<>"", Table1[[#This Row],[India Holiday]]<>""), "Yes", "No") -> No | I70: =IF( AND( WORKDAY(E70-1,1)=E70, _xlfn.CONCAT(F70:G70)="" ), _xlfn.MAXIFS(I$2:I69,C$2:C69,C70,B$2:B69,B70)+1, "" )
B71: =YEAR(E71) -> 2025 | C71: =TEXT(E71,"mmmm") -> September | D71: =TEXT(E71,"dddd") -> Monday | E71: 45908 | H71: =IF(OR(Table1[[#This Row],[US Holiday]]<>"", Table1[[#This Row],[India Holiday]]<>""), "Yes", "No") -> No | I71: =IF( AND( WORKDAY(E71-1,1)=E71, _xlfn.CONCAT(F71:G71)="" ), _xlfn.MAXIFS(I$2:I70,C$2:C70,C71,B$2:B70,B71)+1, "" ) -> 5
B72: =YEAR(E72) -> 2025 | C72: =TEXT(E72,"mmmm") -> September | D72: =TEXT(E72,"dddd") -> Tuesday | E72: 45909 | H72: =IF(OR(Table1[[#This Row],[US Holiday]]<>"", Table1[[#This Row],[India Holiday]]<>""), "Yes", "No") -> No | I72: =IF( AND( WORKDAY(E72-1,1)=E72, _xlfn.CONCAT(F72:G72)="" ), _xlfn.MAXIFS(I$2:I71,C$2:C71,C72,B$2:B71,B72)+1, "" ) -> 6
B73: =YEAR(E73) -> 2025 | C73: =TEXT(E73,"mmmm") -> September | D73: =TEXT(E73,"dddd") -> Wednesday | E73: 45910 | H73: =IF(OR(Table1[[#This Row],[US Holiday]]<>"", Table1[[#This Row],[India Holiday]]<>""), "Yes", "No") -> No | I73: =IF( AND( WORKDAY(E73-1,1)=E73, _xlfn.CONCAT(F73:G73)="" ), _xlfn.MAXIFS(I$2:I72,C$2:C72,C73,B$2:B72,B73)+1, "" ) -> 7
B74: =YEAR(E74) -> 2025 | C74: =TEXT(E74,"mmmm") -> September | D74: =TEXT(E74,"dddd") -> Thursday | E74: 45911 | F74: Simfoni Shutdown | H74: =IF(OR(Table1[[#This Row],[US Holiday]]<>"", Table1[[#This Row],[India Holiday]]<>""), "Yes", "No") -> Yes | I74: =IF( AND( WORKDAY(E74-1,1)=E74, _xlfn.CONCAT(F74:G74)="" ), _xlfn.MAXIFS(I$2:I73,C$2:C73,C74,B$2:B73,B74)+1, "" )
B75: =YEAR(E75) -> 2025 | C75: =TEXT(E75,"mmmm") -> September | D75: =TEXT(E75,"dddd") -> Friday | E75: 45912 | F75: Simfoni Shutdown | H75: =IF(OR(Table1[[#This Row],[US Holiday]]<>"", Table1[[#This Row],[India Holiday]]<>""), "Yes", "No") -> Yes | I75: =IF( AND( WORKDAY(E75-1,1)=E75, _xlfn.CONCAT(F75:G75)="" ), _xlfn.MAXIFS(I$2:I74,C$2:C74,C75,B$2:B74,B75)+1, "" )
B76: =YEAR(E76) -> 2025 | C76: =TEXT(E76,"mmmm") -> September | D76: =TEXT(E76,"dddd") -> Saturday | E76: 45913 | H76: =IF(OR(Table1[[#This Row],[US Holiday]]<>"", Table1[[#This Row],[India Holiday]]<>""), "Yes", "No") -> No | I76: =IF( AND( WORKDAY(E76-1,1)=E76, _xlfn.CONCAT(F76:G76)="" ), _xlfn.MAXIFS(I$2:I75,C$2:C75,C76,B$2:B75,B76)+1, "" )
B77: =YEAR(E77) -> 2025 | C77: =TEXT(E77,"mmmm") -> September | D77: =TEXT(E77,"dddd") -> Sunday | E77: 45914 | H77: =IF(OR(Table1[[#This Row],[US Holiday]]<>"", Table1[[#This Row],[India Holiday]]<>""), "Yes", "No") -> No | I77: =IF( AND( WORKDAY(E77-1,1)=E77, _xlfn.CONCAT(F77:G77)="" ), _xlfn.MAXIFS(I$2:I76,C$2:C76,C77,B$2:B76,B77)+1, "" )
B78: =YEAR(E78) -> 2025 | C78: =TEXT(E78,"mmmm") -> September | D78: =TEXT(E78,"dddd") -> Monday | E78: 45915 | H78: =IF(OR(Table1[[#This Row],[US Holiday]]<>"", Table1[[#This Row],[India Holiday]]<>""), "Yes", "No") -> No | I78: =IF( AND( WORKDAY(E78-1,1)=E78, _xlfn.CONCAT(F78:G78)="" ), _xlfn.MAXIFS(I$2:I77,C$2:C77,C78,B$2:B77,B78)+1, "" ) -> 8
B79: =YEAR(E79) -> 2025 | C79: =TEXT(E79,"mmmm") -> September | D79: =TEXT(E79,"dddd") -> Tuesday | E79: 45916 | H79: =IF(OR(Table1[[#This Row],[US Holiday]]<>"", Table1[[#This Row],[India Holiday]]<>""), "Yes", "No") -> No | I79: =IF( AND( WORKDAY(E79-1,1)=E79, _xlfn.CONCAT(F79:G79)="" ), _xlfn.MAXIFS(I$2:I78,C$2:C78,C79,B$2:B78,B79)+1, "" ) -> 9
B80: =YEAR(E80) -> 2025 | C80: =TEXT(E80,"mmmm") -> September | D80: =TEXT(E80,"dddd") -> Wednesday | E80: 45917 | H80: =IF(OR(Table1[[#This Row],[US Holiday]]<>"", Table1[[#This Row],[India Holiday]]<>""), "Yes", "No") -> No | I80: =IF( AND( WORKDAY(E80-1,1)=E80, _xlfn.CONCAT(F80:G80)="" ), _xlfn.MAXIFS(I$2:I79,C$2:C79,C80,B$2:B79,B80)+1, "" ) -> 10
B81: =YEAR(E81) -> 2025 | C81: =TEXT(E81,"mmmm") -> September | D81: =TEXT(E81,"dddd") -> Thursday | E81: 45918 | H81: =IF(OR(Table1[[#This Row],[US Holiday]]<>"", Table1[[#This Row],[India Holiday]]<>""), "Yes", "No") -> No | I81: =IF( AND( WORKDAY(E81-1,1)=E81, _xlfn.CONCAT(F81:G81)="" ), _xlfn.MAXIFS(I$2:I80,C$2:C80,C81,B$2:B80,B81)+1, "" ) -> 11
B82: =YEAR(E82) -> 2025 | C82: =TEXT(E82,"mmmm") -> September | D82: =TEXT(E82,"dddd") -> Friday | E82: 45919 | H82: =IF(OR(Table1[[#This Row],[US Holiday]]<>"", Table1[[#This Row],[India Holiday]]<>""), "Yes", "No") -> No | I82: =IF( AND( WORKDAY(E82-1,1)=E82, _xlfn.CONCAT(F82:G82)="" ), _xlfn.MAXIFS(I$2:I81,C$2:C81,C82,B$2:B81,B82)+1, "" ) -> 12
B83: =YEAR(E83) -> 2025 | C83: =TEXT(E83,"mmmm") -> September | D83: =TEXT(E83,"dddd") -> Saturday | E83: 45920 | H83: =IF(OR(Table1[[#This Row],[US Holiday]]<>"", Table1[[#This Row],[India Holiday]]<>""), "Yes", "No") -> No | I83: =IF( AND( WORKDAY(E83-1,1)=E83, _xlfn.CONCAT(F83:G83)="" ), _xlfn.MAXIFS(I$2:I82,C$2:C82,C83,B$2:B82,B83)+1, "" )
B84: =YEAR(E84) -> 2025 | C84: =TEXT(E84,"mmmm") -> September | D84: =TEXT(E84,"dddd") -> Sunday | E84: 45921 | H84: =IF(OR(Table1[[#This Row],[US Holiday]]<>"", Table1[[#This Row],[India Holiday]]<>""), "Yes", "No") -> No | I84: =IF( AND( WORKDAY(E84-1,1)=E84, _xlfn.CONCAT(F84:G84)="" ), _xlfn.MAXIFS(I$2:I83,C$2:C83,C84,B$2:B83,B84)+1, "" )
B85: =YEAR(E85) -> 2025 | C85: =TEXT(E85,"mmmm") -> September | D85: =TEXT(E85,"dddd") -> Monday | E85: 45922 | H85: =IF(OR(Table1[[#This Row],[US Holiday]]<>"", Table1[[#This Row],[India Holiday]]<>""), "Yes", "No") -> No | I85: =IF( AND( WORKDAY(E85-1,1)=E85, _xlfn.CONCAT(F85:G85)="" ), _xlfn.MAXIFS(I$2:I84,C$2:C84,C85,B$2:B84,B85)+1, "" ) -> 13
B86: =YEAR(E86) -> 2025 | C86: =TEXT(E86,"mmmm") -> September | D86: =TEXT(E86,"dddd") -> Tuesday | E86: 45923 | H86: =IF(OR(Table1[[#This Row],[US Holiday]]<>"", Table1[[#This Row],[India Holiday]]<>""), "Yes", "No") -> No | I86: =IF( AND( WORKDAY(E86-1,1)=E86, _xlfn.CONCAT(F86:G86)="" ), _xlfn.MAXIFS(I$2:I85,C$2:C85,C86,B$2:B85,B86)+1, "" ) -> 14
B87: =YEAR(E87) -> 2025 | C87: =TEXT(E87,"mmmm") -> September | D87: =TEXT(E87,"dddd") -> Wednesday | E87: 45924 | H87: =IF(OR(Table1[[#This Row],[US Holiday]]<>"", Table1[[#This Row],[India Holiday]]<>""), "Yes", "No") -> No | I87: =IF( AND( WORKDAY(E87-1,1)=E87, _xlfn.CONCAT(F87:G87)="" ), _xlfn.MAXIFS(I$2:I86,C$2:C86,C87,B$2:B86,B87)+1, "" ) -> 15
... B94: =YEAR(E94) -> 2025 | C94: =TEXT(E94,"mmmm") -> October | D94: =TEXT(E94,"dddd") -> Wednesday | E94: 45931 | H94: =IF(OR(Table1[[#This Row],[US Holiday]]<>"", Table1[[#This Row],[India Holiday]]<>""), "Yes", "No") -> No | I94: =IF( AND( WORKDAY(E94-1,1)=E94, _xlfn.CONCAT(F94:G94)="" ), _xlfn.MAXIFS(I$2:I93,C$2:C93,C94,B$2:B93,B94)+1, "" ) -> 1
B95: =YEAR(E95) -> 2025 | C95: =TEXT(E95,"mmmm") -> October | D95: =TEXT(E95,"dddd") -> Thursday | E95: 45932 | G95: Gandhi Jayanti | H95: =IF(OR(Table1[[#This Row],[US Holiday]]<>"", Table1[[#This Row],[India Holiday]]<>""), "Yes", "No") -> Yes | I95: =IF( AND( WORKDAY(E95-1,1)=E95, _xlfn.CONCAT(F95:G95)="" ), _xlfn.MAXIFS(I$2:I94,C$2:C94,C95,B$2:B94,B95)+1, "" )
B96: =YEAR(E96) -> 2025 | C96: =TEXT(E96,"mmmm") -> October | D96: =TEXT(E96,"dddd") -> Friday | E96: 45933 | H96: =IF(OR(Table1[[#This Row],[US Holiday]]<>"", Table1[[#This Row],[India Holiday]]<>""), "Yes", "No") -> No | I96: =IF( AND( WORKDAY(E96-1,1)=E96, _xlfn.CONCAT(F96:G96)="" ), _xlfn.MAXIFS(I$2:I95,C$2:C95,C96,B$2:B95,B96)+1, "" ) -> 2
B97: =YEAR(E97) -> 2025 | C97: =TEXT(E97,"mmmm") -> October | D97: =TEXT(E97,"dddd") -> Saturday | E97: 45934 | H97: =IF(OR(Table1[[#This Row],[US Holiday]]<>"", Table1[[#This Row],[India Holiday]]<>""), "Yes", "No") -> No | I97: =IF( AND( WORKDAY(E97-1,1)=E97, _xlfn.CONCAT(F97:G97)="" ), _xlfn.MAXIFS(I$2:I96,C$2:C96,C97,B$2:B96,B97)+1, "" )
B98: =YEAR(E98) -> 2025 | C98: =TEXT(E98,"mmmm") -> October | D98: =TEXT(E98,"dddd") -> Sunday | E98: 45935 | H98: =IF(OR(Table1[[#This Row],[US Holiday]]<>"", Table1[[#This Row],[India Holiday]]<>""), "Yes", "No") -> No | I98: =IF( AND( WORKDAY(E98-1,1)=E98, _xlfn.CONCAT(F98:G98)="" ), _xlfn.MAXIFS(I$2:I97,C$2:C97,C98,B$2:B97,B98)+1, "" )
B99: =YEAR(E99) -> 2025 | C99: =TEXT(E99,"mmmm") -> October | D99: =TEXT(E99,"dddd") -> Monday | E99: 45936 | H99: =IF(OR(Table1[[#This Row],[US Holiday]]<>"", Table1[[#This Row],[India Holiday]]<>""), "Yes", "No") -> No | I99: =IF( AND( WORKDAY(E99-1,1)=E99, _xlfn.CONCAT(F99:G99)="" ), _xlfn.MAXIFS(I$2:I98,C$2:C98,C99,B$2:B98,B99)+1, "" ) -> 3
B100: =YEAR(E100) -> 2025 | C100: =TEXT(E100,"mmmm") -> October | D100: =TEXT(E100,"dddd") -> Tuesday | E100: 45937 | H100: =IF(OR(Table1[[#This Row],[US Holiday]]<>"", Table1[[#This Row],[India Holiday]]<>""), "Yes", "No") -> No | I100: =IF( AND( WORKDAY(E100-1,1)=E100, _xlfn.CONCAT(F100:G100)="" ), _xlfn.MAXIFS(I$2:I99,C$2:C99,C100,B$2:B99,B100)+1, "" ) -> 4
B101: =YEAR(E101) -> 2025 | C101: =TEXT(E101,"mmmm") -> October | D101: =TEXT(E101,"dddd") -> Wednesday | E101: 45938 | H101: =IF(OR(Table1[[#This Row],[US Holiday]]<>"", Table1[[#This Row],[India Holiday]]<>""), "Yes", "No") -> No | I101: =IF( AND( WORKDAY(E101-1,1)=E101, _xlfn.CONCAT(F101:G101)="" ), _xlfn.MAXIFS(I$2:I100,C$2:C100,C101,B$2:B100,B101)+1, "" ) -> 5
B102: =YEAR(E102) -> 2025 | C102: =TEXT(E102,"mmmm") -> October | D102: =TEXT(E102,"dddd") -> Thursday | E102: 45939 | H102: =IF(OR(Table1[[#This Row],[US Holiday]]<>"", Table1[[#This Row],[India Holiday]]<>""), "Yes", "No") -> No | I102: =IF( AND( WORKDAY(E102-1,1)=E102, _xlfn.CONCAT(F102:G102)="" ), _xlfn.MAXIFS(I$2:I101,C$2:C101,C102,B$2:B101,B102)+1, "" ) -> 6
B103: =YEAR(E103) -> 2025 | C103: =TEXT(E103,"mmmm") -> October | D103: =TEXT(E103,"dddd") -> Friday | E103: 45940 | H103: =IF(OR(Table1[[#This Row],[US Holiday]]<>"", Table1[[#This Row],[India Holiday]]<>""), "Yes", "No") -> No | I103: =IF( AND( WORKDAY(E103-1,1)=E103, _xlfn.CONCAT(F103:G103)="" ), _xlfn.MAXIFS(I$2:I102,C$2:C102,C103,B$2:B102,B103)+1, "" ) -> 7
B104: =YEAR(E104) -> 2025 | C104: =TEXT(E104,"mmmm") -> October | D104: =TEXT(E104,"dddd") -> Saturday | E104: 45941 | H104: =IF(OR(Table1[[#This Row],[US Holiday]]<>"", Table1[[#This Row],[India Holiday]]<>""), "Yes", "No") -> No | I104: =IF( AND( WORKDAY(E104-1,1)=E104, _xlfn.CONCAT(F104:G104)="" ), _xlfn.MAXIFS(I$2:I103,C$2:C103,C104,B$2:B103,B104)+1, "" )
B105: =YEAR(E105) -> 2025 | C105: =TEXT(E105,"mmmm") -> October | D105: =TEXT(E105,"dddd") -> Sunday | E105: 45942 | H105: =IF(OR(Table1[[#This Row],[US Holiday]]<>"", Table1[[#This Row],[India Holiday]]<>""), "Yes", "No") -> No | I105: =IF( AND( WORKDAY(E105-1,1)=E105, _xlfn.CONCAT(F105:G105)="" ), _xlfn.MAXIFS(I$2:I104,C$2:C104,C105,B$2:B104,B105)+1, "" )
B106: =YEAR(E106) -> 2025 | C106: =TEXT(E106,"mmmm") -> October | D106: =TEXT(E106,"dddd") -> Monday | E106: 45943 | H106: =IF(OR(Table1[[#This Row],[US Holiday]]<>"", Table1[[#This Row],[India Holiday]]<>""), "Yes", "No") -> No | I106: =IF( AND( WORKDAY(E106-1,1)=E106, _xlfn.CONCAT(F106:G106)="" ), _xlfn.MAXIFS(I$2:I105,C$2:C105,C106,B$2:B105,B106)+1, "" ) -> 8
B107: =YEAR(E107) -> 2025 | C107: =TEXT(E107,"mmmm") -> October | D107: =TEXT(E107,"dddd") -> Tuesday | E107: 45944 | H107: =IF(OR(Table1[[#This Row],[US Holiday]]<>"", Table1[[#This Row],[India Holiday]]<>""), "Yes", "No") -> No | I107: =IF( AND( WORKDAY(E107-1,1)=E107, _xlfn.CONCAT(F107:G107)="" ), _xlfn.MAXIFS(I$2:I106,C$2:C106,C107,B$2:B106,B107)+1, "" ) -> 9
... B150: =YEAR(E150) -> 2025 | C150: =TEXT(E150,"mmmm") -> November | D150: =TEXT(E150,"dddd") -> Wednesday | E150: 45987 | H150: =IF(OR(Table1[[#This Row],[US Holiday]]<>"", Table1[[#This Row],[India Holiday]]<>""), "Yes", "No") -> No | I150: =IF( AND( WORKDAY(E150-1,1)=E150, _xlfn.CONCAT(F150:G150)="" ), _xlfn.MAXIFS(I$2:I149,C$2:C149,C150,B$2:B149,B150)+1, "" ) -> 18
B151: =YEAR(E151) -> 2025 | C151: =TEXT(E151,"mmmm") -> November | D151: =TEXT(E151,"dddd") -> Thursday | E151: 45988 | F151: Simfoni Shutdown | H151: =IF(OR(Table1[[#This Row],[US Holiday]]<>"", Table1[[#This Row],[India Holiday]]<>""), "Yes", "No") -> Yes | I151: =IF( AND( WORKDAY(E151-1,1)=E151, _xlfn.CONCAT(F151:G151)="" ), _xlfn.MAXIFS(I$2:I150,C$2:C150,C151,B$2:B150,B151)+1, "" )
B152: =YEAR(E152) -> 2025 | C152: =TEXT(E152,"mmmm") -> November | D152: =TEXT(E152,"dddd") -> Friday | E152: 45989 | F152: Simfoni Shutdown | H152: =IF(OR(Table1[[#This Row],[US Holiday]]<>"", Table1[[#This Row],[India Holiday]]<>""), "Yes", "No") -> Yes | I152: =IF( AND( WORKDAY(E152-1,1)=E152, _xlfn.CONCAT(F152:G152)="" ), _xlfn.MAXIFS(I$2:I151,C$2:C151,C152,B$2:B151,B152)+1, "" )
B153: =YEAR(E153) -> 2025 | C153: =TEXT(E153,"mmmm") -> November | D153: =TEXT(E153,"dddd") -> Saturday | E153: 45990 | H153: =IF(OR(Table1[[#This Row],[US Holiday]]<>"", Table1[[#This Row],[India Holiday]]<>""), "Yes", "No") -> No | I153: =IF( AND( WORKDAY(E153-1,1)=E153, _xlfn.CONCAT(F153:G153)="" ), _xlfn.MAXIFS(I$2:I152,C$2:C152,C153,B$2:B152,B153)+1, "" )
B154: =YEAR(E154) -> 2025 | C154: =TEXT(E154,"mmmm") -> November | D154: =TEXT(E154,"dddd") -> Sunday | E154: 45991 | H154: =IF(OR(Table1[[#This Row],[US Holiday]]<>"", Table1[[#This Row],[India Holiday]]<>""), "Yes", "No") -> No | I154: =IF( AND( WORKDAY(E154-1,1)=E154, _xlfn.CONCAT(F154:G154)="" ), _xlfn.MAXIFS(I$2:I153,C$2:C153,C154,B$2:B153,B154)+1, "" )
B155: =YEAR(E155) -> 2025 | C155: =TEXT(E155,"mmmm") -> December | D155: =TEXT(E155,"dddd") -> Monday | E155: 45992 | H155: =IF(OR(Table1[[#This Row],[US Holiday]]<>"", Table1[[#This Row],[India Holiday]]<>""), "Yes", "No") -> No | I155: =IF( AND( WORKDAY(E155-1,1)=E155, _xlfn.CONCAT(F155:G155)="" ), _xlfn.MAXIFS(I$2:I154,C$2:C154,C155,B$2:B154,B155)+1, "" ) -> 1
B156: =YEAR(E156) -> 2025 | C156: =TEXT(E156,"mmmm") -> December | D156: =TEXT(E156,"dddd") -> Tuesday | E156: 45993 | H156: =IF(OR(Table1[[#This Row],[US Holiday]]<>"", Table1[[#This Row],[India Holiday]]<>""), "Yes", "No") -> No | I156: =IF( AND( WORKDAY(E156-1,1)=E156, _xlfn.CONCAT(F156:G156)="" ), _xlfn.MAXIFS(I$2:I155,C$2:C155,C156,B$2:B155,B156)+1, "" ) -> 2
B157: =YEAR(E157) -> 2025 | C157: =TEXT(E157,"mmmm") -> December | D157: =TEXT(E157,"dddd") -> Wednesday | E157: 45994 | H157: =IF(OR(Table1[[#This Row],[US Holiday]]<>"", Table1[[#This Row],[India Holiday]]<>""), "Yes", "No") -> No | I157: =IF( AND( WORKDAY(E157-1,1)=E157, _xlfn.CONCAT(F157:G157)="" ), _xlfn.MAXIFS(I$2:I156,C$2:C156,C157,B$2:B156,B157)+1, "" ) -> 3
B158: =YEAR(E158) -> 2025 | C158: =TEXT(E158,"mmmm") -> December | D158: =TEXT(E158,"dddd") -> Thursday | E158: 45995 | H158: =IF(OR(Table1[[#This Row],[US Holiday]]<>"", Table1[[#This Row],[India Holiday]]<>""), "Yes", "No") -> No | I158: =IF( AND( WORKDAY(E158-1,1)=E158, _xlfn.CONCAT(F158:G158)="" ), _xlfn.MAXIFS(I$2:I157,C$2:C157,C158,B$2:B157,B158)+1, "" ) -> 4
B159: =YEAR(E159) -> 2025 | C159: =TEXT(E159,"mmmm") -> December | D159: =TEXT(E159,"dddd") -> Friday | E159: 45996 | H159: =IF(OR(Table1[[#This Row],[US Holiday]]<>"", Table1[[#This Row],[India Holiday]]<>""), "Yes", "No") -> No | I159: =IF( AND( WORKDAY(E159-1,1)=E159, _xlfn.CONCAT(F159:G159)="" ), _xlfn.MAXIFS(I$2:I158,C$2:C158,C159,B$2:B158,B159)+1, "" ) -> 5
B160: =YEAR(E160) -> 2025 | C160: =TEXT(E160,"mmmm") -> December | D160: =TEXT(E160,"dddd") -> Saturday | E160: 45997 | H160: =IF(OR(Table1[[#This Row],[US Holiday]]<>"", Table1[[#This Row],[India Holiday]]<>""), "Yes", "No") -> No | I160: =IF( AND( WORKDAY(E160-1,1)=E160, _xlfn.CONCAT(F160:G160)="" ), _xlfn.MAXIFS(I$2:I159,C$2:C159,C160,B$2:B159,B160)+1, "" )
B161: =YEAR(E161) -> 2025 | C161: =TEXT(E161,"mmmm") -> December | D161: =TEXT(E161,"dddd") -> Sunday | E161: 45998 | H161: =IF(OR(Table1[[#This Row],[US Holiday]]<>"", Table1[[#This Row],[India Holiday]]<>""), "Yes", "No") -> No | I161: =IF( AND( WORKDAY(E161-1,1)=E161, _xlfn.CONCAT(F161:G161)="" ), _xlfn.MAXIFS(I$2:I160,C$2:C160,C161,B$2:B160,B161)+1, "" )
B162: =YEAR(E162) -> 2025 | C162: =TEXT(E162,"mmmm") -> December | D162: =TEXT(E162,"dddd") -> Monday | E162: 45999 | H162: =IF(OR(Table1[[#This Row],[US Holiday]]<>"", Table1[[#This Row],[India Holiday]]<>""), "Yes", "No") -> No | I162: =IF( AND( WORKDAY(E162-1,1)=E162, _xlfn.CONCAT(F162:G162)="" ), _xlfn.MAXIFS(I$2:I161,C$2:C161,C162,B$2:B161,B162)+1, "" ) -> 6
B163: =YEAR(E163) -> 2025 | C163: =TEXT(E163,"mmmm") -> December | D163: =TEXT(E163,"dddd") -> Tuesday | E163: 46000 | H163: =IF(OR(Table1[[#This Row],[US Holiday]]<>"", Table1[[#This Row],[India Holiday]]<>""), "Yes", "No") -> No | I163: =IF( AND( WORKDAY(E163-1,1)=E163, _xlfn.CONCAT(F163:G163)="" ), _xlfn.MAXIFS(I$2:I162,C$2:C162,C163,B$2:B162,B163)+1, "" ) -> 7
B164: =YEAR(E164) -> 2025 | C164: =TEXT(E164,"mmmm") -> December | D164: =TEXT(E164,"dddd") -> Wednesday | E164: 46001 | H164: =IF(OR(Table1[[#This Row],[US Holiday]]<>"", Table1[[#This Row],[India Holiday]]<>""), "Yes", "No") -> No | I164: =IF( AND( WORKDAY(E164-1,1)=E164, _xlfn.CONCAT(F164:G164)="" ), _xlfn.MAXIFS(I$2:I163,C$2:C163,C164,B$2:B163,B164)+1, "" ) -> 8
... B178: =YEAR(E178) -> 2025 | C178: =TEXT(E178,"mmmm") -> December | D178: =TEXT(E178,"dddd") -> Wednesday | E178: 46015 | H178: =IF(OR(Table1[[#This Row],[US Holiday]]<>"", Table1[[#This Row],[India Holiday]]<>""), "Yes", "No") -> No | I178: =IF( AND( WORKDAY(E178-1,1)=E178, _xlfn.CONCAT(F178:G178)="" ), _xlfn.MAXIFS(I$2:I177,C$2:C177,C178,B$2:B177,B178)+1, "" ) -> 18
B179: =YEAR(E179) -> 2025 | C179: =TEXT(E179,"mmmm") -> December | D179: =TEXT(E179,"dddd") -> Thursday | E179: 46016 | F179: Christmas Day | H179: =IF(OR(Table1[[#This Row],[US Holiday]]<>"", Table1[[#This Row],[India Holiday]]<>""), "Yes", "No") -> Yes | I179: =IF( AND( WORKDAY(E179-1,1)=E179, _xlfn.CONCAT(F179:G179)="" ), _xlfn.MAXIFS(I$2:I178,C$2:C178,C179,B$2:B178,B179)+1, "" )
B180: =YEAR(E180) -> 2025 | C180: =TEXT(E180,"mmmm") -> December | D180: =TEXT(E180,"dddd") -> Friday | E180: 46017 | H180: =IF(OR(Table1[[#This Row],[US Holiday]]<>"", Table1[[#This Row],[India Holiday]]<>""), "Yes", "No") -> No | I180: =IF( AND( WORKDAY(E180-1,1)=E180, _xlfn.CONCAT(F180:G180)="" ), _xlfn.MAXIFS(I$2:I179,C$2:C179,C180,B$2:B179,B180)+1, "" ) -> 19
B181: =YEAR(E181) -> 2025 | C181: =TEXT(E181,"mmmm") -> December | D181: =TEXT(E181,"dddd") -> Saturday | E181: 46018 | H181: =IF(OR(Table1[[#This Row],[US Holiday]]<>"", Table1[[#This Row],[India Holiday]]<>""), "Yes", "No") -> No | I181: =IF( AND( WORKDAY(E181-1,1)=E181, _xlfn.CONCAT(F181:G181)="" ), _xlfn.MAXIFS(I$2:I180,C$2:C180,C181,B$2:B180,B181)+1, "" )
B182: =YEAR(E182) -> 2025 | C182: =TEXT(E182,"mmmm") -> December | D182: =TEXT(E182,"dddd") -> Sunday | E182: 46019 | H182: =IF(OR(Table1[[#This Row],[US Holiday]]<>"", Table1[[#This Row],[India Holiday]]<>""), "Yes", "No") -> No | I182: =IF( AND( WORKDAY(E182-1,1)=E182, _xlfn.CONCAT(F182:G182)="" ), _xlfn.MAXIFS(I$2:I181,C$2:C181,C182,B$2:B181,B182)+1, "" )
B183: =YEAR(E183) -> 2025 | C183: =TEXT(E183,"mmmm") -> December | D183: =TEXT(E183,"dddd") -> Monday | E183: 46020 | H183: =IF(OR(Table1[[#This Row],[US Holiday]]<>"", Table1[[#This Row],[India Holiday]]<>""), "Yes", "No") -> No | I183: =IF( AND( WORKDAY(E183-1,1)=E183, _xlfn.CONCAT(F183:G183)="" ), _xlfn.MAXIFS(I$2:I182,C$2:C182,C183,B$2:B182,B183)+1, "" ) -> 20
B184: =YEAR(E184) -> 2025 | C184: =TEXT(E184,"mmmm") -> December | D184: =TEXT(E184,"dddd") -> Tuesday | E184: 46021 | H184: =IF(OR(Table1[[#This Row],[US Holiday]]<>"", Table1[[#This Row],[India Holiday]]<>""), "Yes", "No") -> No | I184: =IF( AND( WORKDAY(E184-1,1)=E184, _xlfn.CONCAT(F184:G184)="" ), _xlfn.MAXIFS(I$2:I183,C$2:C183,C184,B$2:B183,B184)+1, "" ) -> 21
B185: =YEAR(E185) -> 2025 | C185: =TEXT(E185,"mmmm") -> December | D185: =TEXT(E185,"dddd") -> Wednesday | E185: 46022 | H185: =IF(OR(Table1[[#This Row],[US Holiday]]<>"", Table1[[#This Row],[India Holiday]]<>""), "Yes", "No") -> No | I185: =IF( AND( WORKDAY(E185-1,1)=E185, _xlfn.CONCAT(F185:G185)="" ), _xlfn.MAXIFS(I$2:I184,C$2:C184,C185,B$2:B184,B185)+1, "" ) -> 22
B186: =YEAR(E186) -> 2026 | C186: =TEXT(E186,"mmmm") -> January | D186: =TEXT(E186,"dddd") -> Thursday | E186: 46023 | H186: =IF(OR(Table1[[#This Row],[US Holiday]]<>"", Table1[[#This Row],[India Holiday]]<>""), "Yes", "No") -> No | I186: =IF( AND( WORKDAY(E186-1,1)=E186, _xlfn.CONCAT(F186:G186)="" ), _xlfn.MAXIFS(I$2:I185,C$2:C185,C186,B$2:B185,B186)+1, "" ) -> 1
B187: =YEAR(E187) -> 2026 | C187: =TEXT(E187,"mmmm") -> January | D187: =TEXT(E187,"dddd") -> Friday | E187: 46024 | H187: =IF(OR(Table1[[#This Row],[US Holiday]]<>"", Table1[[#This Row],[India Holiday]]<>""), "Yes", "No") -> No | I187: =IF( AND( WORKDAY(E187-1,1)=E187, _xlfn.CONCAT(F187:G187)="" ), _xlfn.MAXIFS(I$2:I186,C$2:C186,C187,B$2:B186,B187)+1, "" ) -> 2
B188: =YEAR(E188) -> 2026 | C188: =TEXT(E188,"mmmm") -> January | D188: =TEXT(E188,"dddd") -> Saturday | E188: 46025 | H188: =IF(OR(Table1[[#This Row],[US Holiday]]<>"", Table1[[#This Row],[India Holiday]]<>""), "Yes", "No") -> No | I188: =IF( AND( WORKDAY(E188-1,1)=E188, _xlfn.CONCAT(F188:G188)="" ), _xlfn.MAXIFS(I$2:I187,C$2:C187,C188,B$2:B187,B188)+1, "" )
B189: =YEAR(E189) -> 2026 | C189: =TEXT(E189,"mmmm") -> January | D189: =TEXT(E189,"dddd") -> Sunday | E189: 46026 | H189: =IF(OR(Table1[[#This Row],[US Holiday]]<>"", Table1[[#This Row],[India Holiday]]<>""), "Yes", "No") -> No | I189: =IF( AND( WORKDAY(E189-1,1)=E189, _xlfn.CONCAT(F189:G189)="" ), _xlfn.MAXIFS(I$2:I188,C$2:C188,C189,B$2:B188,B189)+1, "" )
B190: =YEAR(E190) -> 2026 | C190: =TEXT(E190,"mmmm") -> January | D190: =TEXT(E190,"dddd") -> Monday | E190: 46027 | H190: =IF(OR(Table1[[#This Row],[US Holiday]]<>"", Table1[[#This Row],[India Holiday]]<>""), "Yes", "No") -> No | I190: =IF( AND( WORKDAY(E190-1,1)=E190, _xlfn.CONCAT(F190:G190)="" ), _xlfn.MAXIFS(I$2:I189,C$2:C189,C190,B$2:B189,B190)+1, "" ) -> 3
B191: =YEAR(E191) -> 2026 | C191: =TEXT(E191,"mmmm") -> January | D191: =TEXT(E191,"dddd") -> Tuesday | E191: 46028 | H191: =IF(OR(Table1[[#This Row],[US Holiday]]<>"", Table1[[#This Row],[India Holiday]]<>""), "Yes", "No") -> No | I191: =IF( AND( WORKDAY(E191-1,1)=E191, _xlfn.CONCAT(F191:G191)="" ), _xlfn.MAXIFS(I$2:I190,C$2:C190,C191,B$2:B190,B191)+1, "" ) -> 4
... B543: =YEAR(E543) -> 2026 | C543: =TEXT(E543,"mmmm") -> December | D543: =TEXT(E543,"dddd") -> Thursday | E543: 46380 | H543: =IF(OR(Table1[[#This Row],[US Holiday]]<>"", Table1[[#This Row],[India Holiday]]<>""), "Yes", "No") -> No | I543: =IF( AND( WORKDAY(E543-1,1)=E543, _xlfn.CONCAT(F543:G543)="" ), _xlfn.MAXIFS(I$2:I542,C$2:C542,C543,B$2:B542,B543)+1, "" ) -> 18
...

Sheet Categories
A2: Priority | C2: Frequency | E2: Status | G2: Category / Workstream | I2: Year | K2: Month | M2: Team Members
A3: Critical | C3: Recurring | E3: Not Started | G3: Internal Reporting | I3: 2025 | K3: January | M3: Entire team
A4: High | C4: Exceptional | E4: In Progress | G4: External Reporting | I4: 2026 | K4: February | M4: CFO
A5: Normal | E5: Blocked / Delayed | G5: Planning & Forecasting | I5: 2027 | K5: March | M5: Director
E6: Done | G6: Close & Accounting | K6: April | M6: Senior Finance Manager
G7: Cash & Treasury | K7: May | M7: Finance Manager
G8: Payroll | K8: June | M8: Senior Finance Analyst
G9: Compliance / Audit | K9: July | M9: FP&A Analyst
G10: Systems / Tools / Admin | K10: August | M10: Junior Finance Analyst
G11: Projects / Strategic Initiatives | K11: September | M11: A/P A/R Analyst
K12: October | M12: Payroll Analyst
K13: November | M13: Controller
K14: December
